Workbook
Name MEV_List: #REF!
Name OverrideList: #REF!

Sheet Home 

Sheet Input Data 
B6: Exposure and Rating Wise client date for PD calculation | R6: Frequency Distribution | U6: Check on rows | V6: =IF(COUNTA(B9:B58)=SUM(S9:S20),"Ok","Error") -> Ok
A8: SL.No | B8: Client Name | C8: Product Type | D8: Industry Type | E8: Rating Agency | F8: Drawn Balance (₹ Cr) | G8: Undrawn Commitment (₹ Cr) | H8: Total Exposure (₹ Cr) | I8: Accrued Interest (₹ Cr) | J8: CCF Applied (%) | K8: Borrower Rating | L8: Final EAD | M8: Borrower Rating (aligned) | N8: SICR(Y/N)* | O8: Stage | R8: Rating | S8: Frequency | T8: Stage 1 | U8: Stage 2 | V8: Stage 3
A9: 1 | B9: National Thermal Power Corporation | C9: Lease Financing | D9: Power | E9: CRISIL | F9: 125.06 | G9: 125 | H9: 250 | I9: 2 | J9: 1 | K9: AAA | L9: =F9+(G9*J9)+I9 -> 252.06 | M9: AAA | N9: N | O9: =IF(N9="N","Stage 1","Stage 2") -> Stage 1 | R9: AAA | S9: =COUNTIF($M$9:$M$50,R9) -> 4 | T9: =SUMIFS($L$9:$L$22,$M$9:$M$22,$R9,$O$9:$O$22,$T$8) -> 16859.79 | U9: =SUMIFS($L$9:$L$22,$M$9:$M$22,$R9,$O$9:$O$22,$U$8) -> 0 | V9: =SUMIFS($L$9:$L$22,$M$9:$M$22,$R9,$O$9:$O$22,$V$8) -> 0
A10: 2 | B10: National Thermal Power Corporation Renewable Energy Limited (PPA WITH INDIAN RAILWAY) | C10: Term Loan | D10: Power | E10: India Rating | F10: 3100 | G10: 1900 | H10: 0 | I10: 0 | J10: 0.5 | K10: IND AAA | L10: =F10+(G10*J10)+I10 -> 4050 | M10: AAA | N10: N | O10: =IF(N10="N","Stage 1","Stage 2") -> Stage 1 | R10: AA+ | S10: =COUNTIF($M$9:$M$50,R10) -> 1 | T10: =SUMIFS($L$9:$L$22,$M$9:$M$22,$R10,$O$9:$O$22,$T$8) -> 1103.85 | U10: =SUMIFS($L$9:$L$22,$M$9:$M$22,$R10,$O$9:$O$22,$U$8) -> 0 | V10: =SUMIFS($L$9:$L$22,$M$9:$M$22,$R10,$O$9:$O$22,$V$8) -> 0
A11: 3 | B11: National Thermal Power Corporation (SUPPLY TO INDIAN RAILWAY) | C11: Term Loan | D11: Power | E11: CRISIL | F11: 0 | G11: 5000 | H11: 0 | I11: 0 | J11: 0.5 | K11: AAA | L11: =F11+(G11*J11)+I11 -> 2500 | M11: AAA | N11: N | O11: =IF(N11="N","Stage 1","Stage 2") -> Stage 1 | R11: AA | S11: =COUNTIF($M$9:$M$50,R11) -> 1 | T11: =SUMIFS($L$9:$L$22,$M$9:$M$22,$R11,$O$9:$O$22,$T$8) -> 12103.75 | U11: =SUMIFS($L$9:$L$22,$M$9:$M$22,$R11,$O$9:$O$22,$U$8) -> 0 | V11: =SUMIFS($L$9:$L$22,$M$9:$M$22,$R11,$O$9:$O$22,$V$8) -> 0
A12: 4 | B12: Angul Sukinda Railway Line | C12: Term Loan | D12: Railways | E12: India Rating | F12: 2472.2 | G12: 0 | H12: 2472 | I12: 18.21 | J12: 0 | K12: IND BB+ | L12: =F12+(G12*J12)+I12 -> 2490.41 | M12: BB+ | N12: N | O12: =IF(N12="N","Stage 1","Stage 2") -> Stage 1 | R12: AA- | S12: =COUNTIF($M$9:$M$50,R12) -> 0 | T12: =SUMIFS($L$9:$L$22,$M$9:$M$22,$R12,$O$9:$O$22,$T$8) -> 0 | U12: =SUMIFS($L$9:$L$22,$M$9:$M$22,$R12,$O$9:$O$22,$U$8) -> 0 | V12: =SUMIFS($L$9:$L$22,$M$9:$M$22,$R12,$O$9:$O$22,$V$8) -> 0
A13: 5 | B13: Surat Integrated Transportation Development Corporation Limited (RLDA) | C13: Term Loan | D13: Railways | E13: Unrated | F13: 0 | G13: 200 | H13: 0 | I13: 0 | J13: 1 | K13: Unrated | L13: =F13+(G13*J13)+I13 -> 200 | M13: Unrated | N13: N | O13: =IF(N13="N","Stage 1","Stage 2") -> Stage 1 | R13: A+ | S13: =COUNTIF($M$9:$M$50,R13) -> 1 | T13: =SUMIFS($L$9:$L$22,$M$9:$M$22,$R13,$O$9:$O$22,$T$8) -> 2964.5 | U13: =SUMIFS($L$9:$L$22,$M$9:$M$22,$R13,$O$9:$O$22,$U$8) -> 0 | V13: =SUMIFS($L$9:$L$22,$M$9:$M$22,$R13,$O$9:$O$22,$V$8) -> 0
A14: 6 | B14: Bhartiya Rail Corporation Limited | C14: Term Loan | D14: Power | E14: ICRA | F14: 1096.96 | G14: 0 | H14: 1096.96 | I14: 6.89 | J14: 0 | K14: AA+ | L14: =F14+(G14*J14)+I14 -> 1103.85 | M14: AA+ | N14: N | O14: =IF(N14="N","Stage 1","Stage 2") -> Stage 1 | R14: A | S14: =COUNTIF($M$9:$M$50,R14) -> 1 | T14: =SUMIFS($L$9:$L$22,$M$9:$M$22,$R14,$O$9:$O$22,$T$8) -> 6320.7575 | U14: =SUMIFS($L$9:$L$22,$M$9:$M$22,$R14,$O$9:$O$22,$U$8) -> 0 | V14: =SUMIFS($L$9:$L$22,$M$9:$M$22,$R14,$O$9:$O$22,$V$8) -> 0
A15: 7 | B15: Chhattisgarh State Power Generation Ltd. | C15: Term Loan | D15: Power | E15: India Rating | F15: 1.51 | G15: 12638.49 | H15: 12640 | I15: 0.002459 | J15: 0.5 | K15: IND A | L15: =F15+(G15*J15)+I15 -> 6320.7575 | M15: A | N15: N | O15: =IF(N15="N","Stage 1","Stage 2") -> Stage 1 | R15: A- | S15: =COUNTIF($M$9:$M$50,R15) -> 3 | T15: =SUMIFS($L$9:$L$22,$M$9:$M$22,$R15,$O$9:$O$22,$T$8) -> 12522.26 | U15: =SUMIFS($L$9:$L$22,$M$9:$M$22,$R15,$O$9:$O$22,$U$8) -> 0 | V15: =SUMIFS($L$9:$L$22,$M$9:$M$22,$R15,$O$9:$O$22,$V$8) -> 0
A16: 8 | B16: Talcher Fertilizer Limited | C16: Term Loan | D16: Fertilizers | E16: ICRA | F16: 1259.92 | G16: 2740.08 | H16: 4000 | I16: 9.79 | J16: 0.5 | K16: BBB+ | L16: =F16+(G16*J16)+I16 -> 2639.75 | M16: BBB+ | N16: N | O16: =IF(N16="N","Stage 1","Stage 2") -> Stage 1 | R16: BBB+ | S16: =COUNTIF($M$9:$M$50,R16) -> 1 | T16: =SUMIFS($L$9:$L$22,$M$9:$M$22,$R16,$O$9:$O$22,$T$8) -> 2639.75 | U16: =SUMIFS($L$9:$L$22,$M$9:$M$22,$R16,$O$9:$O$22,$U$8) -> 0 | V16: =SUMIFS($L$9:$L$22,$M$9:$M$22,$R16,$O$9:$O$22,$V$8) -> 0
A17: 9 | B17: Patratu Vidyut Utpadan Nigam Limited | C17: Term Loan | D17: Power | E17: ICRA | F17: 0 | G17: 3389 | H17: 3389 | I17: 0 | J17: =+J16 -> 0.5 | K17: A- | L17: =F17+(G17*J17)+I17 -> 1694.5 | M17: A- | N17: N | O17: =IF(N17="N","Stage 1","Stage 2") -> Stage 1 | R17: BBB | S17: =COUNTIF($M$9:$M$50,R17) -> 0 | T17: =SUMIFS($L$9:$L$22,$M$9:$M$22,$R17,$O$9:$O$22,$T$8) -> 0 | U17: =SUMIFS($L$9:$L$22,$M$9:$M$22,$R17,$O$9:$O$22,$U$8) -> 0 | V17: =SUMIFS($L$9:$L$22,$M$9:$M$22,$R17,$O$9:$O$22,$V$8) -> 0
A18: 10 | B18: Haryana Power Generation Corporation Limited | C18: Term Loan | D18: Power | E18: India Rating | F18: 0 | G18: 5929 | H18: 5929 | I18: 0 | J18: 0.5 | K18: Ind A+ | L18: =F18+(G18*J18)+I18 -> 2964.5 | M18: A+ | N18: N | O18: =IF(N18="N","Stage 1","Stage 2") -> Stage 1 | R18: BBB- | S18: =COUNTIF($M$9:$M$50,R18) -> 0 | T18: =SUMIFS($L$9:$L$22,$M$9:$M$22,$R18,$O$9:$O$22,$T$8) -> 0 | U18: =SUMIFS($L$9:$L$22,$M$9:$M$22,$R18,$O$9:$O$22,$U$8) -> 0 | V18: =SUMIFS($L$9:$L$22,$M$9:$M$22,$R18,$O$9:$O$22,$V$8) -> 0
A19: 11 | B19: Maharashtra State Power Generation Corporation Limited | C19: Term Loan | D19: Power | E19: Acuite Rating | F19: 1017.96 | G19: 9542.04 | H19: =F19+G19 -> 10560 | I19: 6.87 | J19: 0.5 | K19: A- | L19: =F19+(G19*J19)+I19 -> 5795.85 | M19: A- | N19: N | O19: =IF(N19="N","Stage 1","Stage 2") -> Stage 1 | R19: BB+ | S19: =COUNTIF($M$9:$M$50,R19) -> 1 | T19: =SUMIFS($L$9:$L$22,$M$9:$M$22,$R19,$O$9:$O$22,$T$8) -> 2490.41 | U19: =SUMIFS($L$9:$L$22,$M$9:$M$22,$R19,$O$9:$O$22,$U$8) -> 0 | V19: =SUMIFS($L$9:$L$22,$M$9:$M$22,$R19,$O$9:$O$22,$V$8) -> 0
A20: 12 | B20: Dedicated Freight Corridor Corporation of India Limited | C20: Term Loan | D20: Railways | E20: CRISIL | F20: 9821 | G20: 179 | H20: =F20+G20 -> 10000 | I20: 200.93 | J20: 0.2 | K20: AAA | L20: =F20+(G20*J20)+I20 -> 10057.73 | M20: AAA | N20: N | O20: =IF(N20="N","Stage 1","Stage 2") -> Stage 1 | R20: Unrated | S20: =COUNTIF($M$9:$M$50,R20) -> 1 | T20: =SUMIFS($L$9:$L$22,$M$9:$M$22,$R20,$O$9:$O$22,$T$8) -> 200 | U20: =SUMIFS($L$9:$L$22,$M$9:$M$22,$R20,$O$9:$O$22,$U$8) -> 0 | V20: =SUMIFS($L$9:$L$22,$M$9:$M$22,$R20,$O$9:$O$22,$V$8) -> 0
A21: 13 | B21: Maharashtra State Power Generation Corporation Limited | C21: Term Loan | D21: Power | E21: Acuite Rating | F21: 5000 | G21: 0 | H21: =F21+G21 -> 5000 | I21: 31.91 | J21: 0.2 | K21: A- | L21: =F21+(G21*J21)+I21 -> 5031.91 | M21: A- | N21: N | O21: =IF(N21="N","Stage 1","Stage 2") -> Stage 1
A22: 14 | B22: Hindustan Urvarak and Rasayan Limited | C22: Term Loan | D22: Fertilizers | E22: India Rating | F22: 11904.32 | G22: 938 | H22: =F22+G22 -> 12842.32 | I22: 11.83 | J22: 0.2 | K22: IND AA | L22: =F22+(G22*J22)+I22 -> 12103.75 | M22: AA | N22: N | O22: =IF(N22="N","Stage 1","Stage 2") -> Stage 1 | R22: * SICR Assumption: Exposures where the Days Past Due (DPD) exceed 30 days are classified under Stage 2.
A23: =A22+1 -> 15
A24: =A23+1 -> 16
A25: =A24+1 -> 17
A26: =A25+1 -> 18
A27: =A26+1 -> 19
A28: =A27+1 -> 20
A29: =A28+1 -> 21
A30: =A29+1 -> 22
A31: =A30+1 -> 23
A32: =A31+1 -> 24
A33: =A32+1 -> 25
A34: =A33+1 -> 26
... A58: =A57+1 -> 50

Sheet TTC PD
C6: Rating wise TTC PD*: | G6: Screeen shot of Crisil PD Matrix
C7: CRISIL RATING | D7: CRISIL Default TTC PD
C8: ='Input Data '!R9 -> AAA | D8: 0.0003
C9: ='Input Data '!R10 -> AA+ | D9: 0.0029
C10: ='Input Data '!R11 -> AA | D10: 0.0029
C11: ='Input Data '!R12 -> AA- | D11: 0.0029
C12: ='Input Data '!R13 -> A+ | D12: 0.0066
C13: ='Input Data '!R14 -> A | D13: 0.0066
C14: ='Input Data '!R15 -> A- | D14: 0.0066
C15: ='Input Data '!R16 -> BBB+ | D15: 0.0221
C16: ='Input Data '!R17 -> BBB | D16: 0.0221
C17: ='Input Data '!R18 -> BBB- | D17: 0.0221
C18: ='Input Data '!R19 -> BB+ | D18: 0.0992
C19: ='Input Data '!R20 -> Unrated | D19: 0.0992
C21: * Note: PD's to be changed on annual basis | G21: Link For Crisil PD's
G22: https://www.crisil.com/content/dam/crisil/our-analysis/publications/default-study/crisil-ratings-annual-default-and-ratings-transition-study-fy-2025.pdf

Sheet MEV Data
B6: Macroeconomic Variable: Historical and Forecasted Values
B8: Series Title | C8: 2020 | D8: 2021 | E8: 2022 | F8: 2023 | G8: 2024 | H8: 2025 | I8: 2026 | J8: 2027 | K8: 2028 | L8: 2029 | M8: 2030 | N8: 2031 | O8: LTM(Long Term Mean) | P8: SD | Q8: CV
B9: Unemployment Rate | C9: 8.662 | D9: 7.365 | E9: 5.3 | F9: 4.939 | G9: 4.939 | H9: 4.939 | I9: 4.939 | J9: 4.939 | K9: 4.939 | L9: 4.939 | M9: 4.939 | N9: 4.939 | O9: =AVERAGE(C9:I9) -> 5.869 | P9: =_xlfn.STDEV.P(C9:I9) -> 1.4052059 | Q9: =(P9/O9) -> 0.23942851
B10: GDP | C10: -5.778 | D10: 9.69 | E10: 7.609 | F10: 7.21 | G10: 7.099 | H10: 7.618 | I10: 6.478 | J10: 6.529 | K10: 6.5 | L10: 6.52 | M10: 6.503 | N10: 6.514 | O10: =AVERAGE(C10:I10) -> 5.7037143 | P10: =_xlfn.STDEV.P(C10:I10) -> 4.7783751 | Q10: =P10/O10 -> 0.8377655
B11: Inflation | C11: 4.769 | D11: 6.154 | E11: 5.512 | F11: 6.634 | G11: 5.37 | H11: 4.639 | I11: 2.091 | J11: 4.715 | K11: 4 | L11: 4 | M11: 4 | N11: 4 | O11: =AVERAGE(C11:I11) -> 5.0241429 | P11: =_xlfn.STDEV.P(C11:I11) -> 1.3650012 | Q11: =(P11/O11)*100 -> 27.168838
B12: Govt_Revenue | C12: 36044.776 | D12: 48228.993 | E12: 54137.903 | F12: 61815.407 | G12: 68141.219 | H12: 72847.417 | I12: 81625.055 | J12: 90990.196 | K12: 101388.78 | L12: 113003.81 | M12: 125934.9 | N12: 140367.34 | O12: =AVERAGE(C12:I12) -> 60405.824 | P12: =_xlfn.STDEV.P(C12:I12) -> 14382.007 | Q12: =(P12/O12)*100 -> 23.808975
B13: General government gross debt | C13: 90.562 | D13: 85.713 | E13: 84.598 | F13: 85.01 | G13: 84.782 | H13: 84.075 | I13: 83.362 | J13: 82.546 | K13: 81.663 | L13: 80.609 | M13: 79.465 | N13: 77.689 | O13: =AVERAGE(C13:I13) -> 85.443143 | P13: =_xlfn.STDEV.P(C13:I13) -> 2.1979692 | Q13: =(P13/O13)*100 -> 2.5724349

Sheet MEV_Index
B6: Macro Economic Variable (MEV):
A7: A | B7: Variable as per Policy | C7: Variable 1 | D7: Variable 2
B8: Selected MEV | C8: ='MEV Data'!B10 -> GDP | D8: ='MEV Data'!B12 -> Govt_Revenue
B9: Weights | C9: 0.5 | D9: =100%-C9 -> 0.5
A11: B | B11: Variable | C11: =D11-1 -> 2020 | D11: =E11-1 -> 2021 | E11: =F11-1 -> 2022 | F11: =G11-1 -> 2023 | G11: =H11-1 -> 2024 | H11: =I11-1 -> 2025 | I11: 2026 | J11: =I11+1 -> 2027 | K11: =J11+1 -> 2028 | L11: =K11+1 -> 2029 | M11: =L11+1 -> 2030 | N11: =M11+1 -> 2031
B12: =C8 -> GDP | C12: {=_xlfn.XLOOKUP($C$8,'MEV Data'!$B$9:$B$13,'MEV Data'!$C$9:$N$13,"Not Found")} -> -5.778 | D12: 9.69 | E12: 7.609 | F12: 7.21 | G12: 7.099 | H12: 7.618 | I12: 6.478 | J12: 6.529 | K12: 6.5 | L12: 6.52 | M12: 6.503 | N12: 6.514
B13: =D8 -> Govt_Revenue | C13: {=_xlfn.XLOOKUP($D$8,'MEV Data'!$B$9:$B$13,'MEV Data'!$C$9:$N$13,"Not Found")} -> 36044.776 | D13: 48228.993 | E13: 54137.903 | F13: 61815.407 | G13: 68141.219 | H13: 72847.417 | I13: 81625.055 | J13: 90990.196 | K13: 101388.78 | L13: 113003.81 | M13: 125934.9 | N13: 140367.34
A16: C | B16: Scenerio Development
C17: =B12 -> GDP | D17: =B13 -> Govt_Revenue
B18: Long Term Mean | C18: =AVERAGE(C12:I12) -> 5.7037143 | D18: =AVERAGE(C13:I13) -> 60405.824
B19: Standard Deviation | C19: =_xlfn.STDEV.P(C12:I12) -> 4.7783751 | D19: =_xlfn.STDEV.P(C13:I13) -> 14382.007
A21: D | B21: Z_Factor
B22: Variable | C22: =C11 -> 2020 | D22: =C22+1 -> 2021 | E22: =D22+1 -> 2022 | F22: =E22+1 -> 2023 | G22: =F22+1 -> 2024 | H22: =G22+1 -> 2025 | I22: =H22+1 -> 2026 | J22: =I22+1 -> 2027 | K22: =J22+1 -> 2028 | ... N22: =M22+1 -> 2031
B23: =B12 -> GDP | C23: =(C12-$C$18)/$C$19 -> -2.4028491 | D23: =(D12-$C$18)/$C$19 -> 0.83423458 | E23: =(E12-$C$18)/$C$19 -> 0.39873088 | F23: =(F12-$C$18)/$C$19 -> 0.3152297 | G23: =(G12-$C$18)/$C$19 -> 0.29200004 | H23: =(H12-$C$18)/$C$19 -> 0.40061437 | I23: =(I12-$C$18)/$C$19 -> 0.16203954 | J23: =(J12-$C$18)/$C$19 -> 0.17271263 | ... N23: =(N12-$C$18)/$C$19 -> 0.16957349
B24: =B13 -> Govt_Revenue | C24: =(C13-$D$18)/$D$19 -> -1.6938559 | D24: =(D13-$D$18)/$D$19 -> -0.84667118 | E24: =(E13-$D$18)/$D$19 -> -0.43581686 | F24: =(F13-$D$18)/$D$19 -> 0.098010151 | G24: =(G13-$D$18)/$D$19 -> 0.53785223 | H24: =(H13-$D$18)/$D$19 -> 0.8650804 | I24: =(I13-$D$18)/$D$19 -> 1.4754012 | J24: =(J13-$D$18)/$D$19 -> 2.1265718 | ... N24: =(N13-$D$18)/$D$19 -> 5.55983
A26: E | B26: MEV_Index
B27: Variable | C27: =C22 -> 2020 | D27: =C27+1 -> 2021 | E27: =D27+1 -> 2022 | F27: =E27+1 -> 2023 | G27: =F27+1 -> 2024 | H27: =G27+1 -> 2025 | I27: =H27+1 -> 2026 | J27: =I27+1 -> 2027 | K27: =J27+1 -> 2028 | ... N27: =M27+1 -> 2031
B28: Index | C28: =C23*$C$9+C24*$D$9 -> -2.0483525 | D28: =D23*$C$9+D24*$D$9 -> -0.0062183021 | E28: =E23*$C$9+E24*$D$9 -> -0.018542986 | F28: =F23*$C$9+F24*$D$9 -> 0.20661992 | G28: =G23*$C$9+G24*$D$9 -> 0.41492613 | H28: =H23*$C$9+H24*$D$9 -> 0.63284738 | I28: =I23*$C$9+I24*$D$9 -> 0.81872036 | J28: =J23*$C$9+J24*$D$9 -> 1.1496422 | ... N28: =N23*$C$9+N24*$D$9 -> 2.8647018

Sheet MEV Scenario
A7: MEV Scenario
A9: Base
A10: Variable | B10: =MEV_Index!C11 -> 2020 | C10: =MEV_Index!D11 -> 2021 | D10: =MEV_Index!E11 -> 2022 | E10: =MEV_Index!F11 -> 2023 | F10: =MEV_Index!G11 -> 2024 | G10: =MEV_Index!H11 -> 2025 | H10: =MEV_Index!I11 -> 2026 | I10: =MEV_Index!J11 -> 2027 | ... M10: =MEV_Index!N11 -> 2031
A11: MEV_Index | B11: =MEV_Index!C28 -> -2.0483525 | C11: =MEV_Index!D28 -> -0.0062183021 | D11: =MEV_Index!E28 -> -0.018542986 | E11: =MEV_Index!F28 -> 0.20661992 | F11: =MEV_Index!G28 -> 0.41492613 | G11: =MEV_Index!H28 -> 0.63284738 | H11: =MEV_Index!I28 -> 0.81872036 | I11: =MEV_Index!J28 -> 1.1496422 | ... M11: =MEV_Index!N28 -> 2.8647018
A14: Upturn
A15: Variable | B15: =B10 -> 2020 | C15: =C10 -> 2021 | D15: =D10 -> 2022 | E15: =E10 -> 2023 | F15: =F10 -> 2024 | G15: =G10 -> 2025 | H15: =H10 -> 2026 | I15: =I10 -> 2027 | ... M15: =M10 -> 2031
A16: MEV_Index | B16: =IF(B11<0,B11*Admin!$B$14,B11*Admin!$B$15) -> -1.8435173 | C16: =IF(C11<0,C11*Admin!$B$14,C11*Admin!$B$15) -> -0.0055964719 | D16: =IF(D11<0,D11*Admin!$B$14,D11*Admin!$B$15) -> -0.016688688 | E16: =IF(E11<0,E11*Admin!$B$14,E11*Admin!$B$15) -> 0.22728192 | F16: =IF(F11<0,F11*Admin!$B$14,F11*Admin!$B$15) -> 0.45641875 | G16: =IF(G11<0,G11*Admin!$B$14,G11*Admin!$B$15) -> 0.69613212 | H16: =IF(H11<0,H11*Admin!$B$14,H11*Admin!$B$15) -> 0.9005924 | I16: =IF(I11<0,I11*Admin!$B$14,I11*Admin!$B$15) -> 1.2646064 | ... M16: =IF(M11<0,M11*Admin!$B$14,M11*Admin!$B$15) -> 3.1511719
A19: Downturn
A20: Variable | B20: =B15 -> 2020 | C20: =C15 -> 2021 | D20: =D15 -> 2022 | E20: =E15 -> 2023 | F20: =F15 -> 2024 | G20: =G15 -> 2025 | H20: =H15 -> 2026 | I20: =I15 -> 2027 | ... M20: =M15 -> 2031
A21: MEV_Index | B21: =IF(B11<0,B11*Admin!$B$15,B11*Admin!$B$14) -> -2.2531878 | C21: =IF(C11<0,C11*Admin!$B$15,C11*Admin!$B$14) -> -0.0068401323 | D21: =IF(D11<0,D11*Admin!$B$15,D11*Admin!$B$14) -> -0.020397285 | E21: =IF(E11<0,E11*Admin!$B$15,E11*Admin!$B$14) -> 0.18595793 | F21: =IF(F11<0,F11*Admin!$B$15,F11*Admin!$B$14) -> 0.37343352 | G21: =IF(G11<0,G11*Admin!$B$15,G11*Admin!$B$14) -> 0.56956265 | H21: =IF(H11<0,H11*Admin!$B$15,H11*Admin!$B$14) -> 0.73684832 | I21: =IF(I11<0,I11*Admin!$B$15,I11*Admin!$B$14) -> 1.034678 | ... M21: =IF(M11<0,M11*Admin!$B$15,M11*Admin!$B$14) -> 2.5782316

Sheet Vasicek
B6: Forecast Probability of Default
B8: Base | E8: 2026 | F8: =E8+1 -> 2027 | G8: =F8+1 -> 2028 | H8: =G8+1 -> 2029 | I8: =H8+1 -> 2030 | J8: =I8+1 -> 2031
B9: Grades | C9: TTC | D9: Asset Correlation | E9: ='MEV Scenario'!H11 -> 0.81872036 | F9: ='MEV Scenario'!I11 -> 1.1496422 | G9: ='MEV Scenario'!J11 -> 1.5081213 | H9: ='MEV Scenario'!K11 -> 1.9140184 | I9: ='MEV Scenario'!L11 -> 2.3617974 | J9: ='MEV Scenario'!M11 -> 2.8647018
B10: ='TTC PD'!C8 -> AAA | C10: ='TTC PD'!D8 -> 0.0003 | D10: =(0.12*(1-EXP(-50*C10))/(1-EXP(-50)))+0.24*(1-(1-EXP(-50*C10))/(1-EXP(-50))) -> 0.23821343 | E10: =IFERROR( IF( NORMSDIST((NORMSINV($C10)-SQRT($D10)*E$9)/SQRT(1-$D10))<0.03%, 0.03%, NORMSDIST((NORMSINV($C10)-SQRT($D10)*E$9)/SQRT(1-$D10)) ), 0.03% ) -> 0.0003 | F10: =IFERROR( IF( NORMSDIST((NORMSINV($C10)-SQRT($D10)*F$9)/SQRT(1-$D10))<0.03%, 0.03%, NORMSDIST((NORMSINV($C10)-SQRT($D10)*F$9)/SQRT(1-$D10)) ), 0.03% ) -> 0.0003 | G10: =IFERROR( IF( NORMSDIST((NORMSINV($C10)-SQRT($D10)*G$9)/SQRT(1-$D10))<0.03%, 0.03%, NORMSDIST((NORMSINV($C10)-SQRT($D10)*G$9)/SQRT(1-$D10)) ), 0.03% ) -> 0.0003 | H10: =IFERROR( IF( NORMSDIST((NORMSINV($C10)-SQRT($D10)*H$9)/SQRT(1-$D10))<0.03%, 0.03%, NORMSDIST((NORMSINV($C10)-SQRT($D10)*H$9)/SQRT(1-$D10)) ), 0.03% ) -> 0.0003 | I10: =IFERROR( IF( NORMSDIST((NORMSINV($C10)-SQRT($D10)*I$9)/SQRT(1-$D10))<0.03%, 0.03%, NORMSDIST((NORMSINV($C10)-SQRT($D10)*I$9)/SQRT(1-$D10)) ), 0.03% ) -> 0.0003 | J10: =IFERROR( IF( NORMSDIST((NORMSINV($C10)-SQRT($D10)*J$9)/SQRT(1-$D10))<0.03%, 0.03%, NORMSDIST((NORMSINV($C10)-SQRT($D10)*J$9)/SQRT(1-$D10)) ), 0.03% ) -> 0.0003
B11: ='TTC PD'!C9 -> AA+ | C11: ='TTC PD'!D9 -> 0.0029 | D11: =(0.12*(1-EXP(-50*C11))/(1-EXP(-50)))+0.24*(1-(1-EXP(-50*C11))/(1-EXP(-50))) -> 0.22380268 | E11: =IFERROR( IF( NORMSDIST((NORMSINV($C11)-SQRT($D11)*E$9)/SQRT(1-$D11))<0.03%, 0.03%, NORMSDIST((NORMSINV($C11)-SQRT($D11)*E$9)/SQRT(1-$D11)) ), 0.03% ) -> 0.0003 | F11: =IFERROR( IF( NORMSDIST((NORMSINV($C11)-SQRT($D11)*F$9)/SQRT(1-$D11))<0.03%, 0.03%, NORMSDIST((NORMSINV($C11)-SQRT($D11)*F$9)/SQRT(1-$D11)) ), 0.03% ) -> 0.0003 | G11: =IFERROR( IF( NORMSDIST((NORMSINV($C11)-SQRT($D11)*G$9)/SQRT(1-$D11))<0.03%, 0.03%, NORMSDIST((NORMSINV($C11)-SQRT($D11)*G$9)/SQRT(1-$D11)) ), 0.03% ) -> 0.0003 | H11: =IFERROR( IF( NORMSDIST((NORMSINV($C11)-SQRT($D11)*H$9)/SQRT(1-$D11))<0.03%, 0.03%, NORMSDIST((NORMSINV($C11)-SQRT($D11)*H$9)/SQRT(1-$D11)) ), 0.03% ) -> 0.0003 | I11: =IFERROR( IF( NORMSDIST((NORMSINV($C11)-SQRT($D11)*I$9)/SQRT(1-$D11))<0.03%, 0.03%, NORMSDIST((NORMSINV($C11)-SQRT($D11)*I$9)/SQRT(1-$D11)) ), 0.03% ) -> 0.0003 | J11: =IFERROR( IF( NORMSDIST((NORMSINV($C11)-SQRT($D11)*J$9)/SQRT(1-$D11))<0.03%, 0.03%, NORMSDIST((NORMSINV($C11)-SQRT($D11)*J$9)/SQRT(1-$D11)) ), 0.03% ) -> 0.0003
B12: ='TTC PD'!C10 -> AA | C12: ='TTC PD'!D10 -> 0.0029 | D12: =(0.12*(1-EXP(-50*C12))/(1-EXP(-50)))+0.24*(1-(1-EXP(-50*C12))/(1-EXP(-50))) -> 0.22380268 | E12: =IFERROR( IF( NORMSDIST((NORMSINV($C12)-SQRT($D12)*E$9)/SQRT(1-$D12))<0.03%, 0.03%, NORMSDIST((NORMSINV($C12)-SQRT($D12)*E$9)/SQRT(1-$D12)) ), 0.03% ) -> 0.0003 | F12: =IFERROR( IF( NORMSDIST((NORMSINV($C12)-SQRT($D12)*F$9)/SQRT(1-$D12))<0.03%, 0.03%, NORMSDIST((NORMSINV($C12)-SQRT($D12)*F$9)/SQRT(1-$D12)) ), 0.03% ) -> 0.0003 | G12: =IFERROR( IF( NORMSDIST((NORMSINV($C12)-SQRT($D12)*G$9)/SQRT(1-$D12))<0.03%, 0.03%, NORMSDIST((NORMSINV($C12)-SQRT($D12)*G$9)/SQRT(1-$D12)) ), 0.03% ) -> 0.0003 | H12: =IFERROR( IF( NORMSDIST((NORMSINV($C12)-SQRT($D12)*H$9)/SQRT(1-$D12))<0.03%, 0.03%, NORMSDIST((NORMSINV($C12)-SQRT($D12)*H$9)/SQRT(1-$D12)) ), 0.03% ) -> 0.0003 | I12: =IFERROR( IF( NORMSDIST((NORMSINV($C12)-SQRT($D12)*I$9)/SQRT(1-$D12))<0.03%, 0.03%, NORMSDIST((NORMSINV($C12)-SQRT($D12)*I$9)/SQRT(1-$D12)) ), 0.03% ) -> 0.0003 | J12: =IFERROR( IF( NORMSDIST((NORMSINV($C12)-SQRT($D12)*J$9)/SQRT(1-$D12))<0.03%, 0.03%, NORMSDIST((NORMSINV($C12)-SQRT($D12)*J$9)/SQRT(1-$D12)) ), 0.03% ) -> 0.0003
B13: ='TTC PD'!C11 -> AA- | C13: ='TTC PD'!D11 -> 0.0029 | D13: =(0.12*(1-EXP(-50*C13))/(1-EXP(-50)))+0.24*(1-(1-EXP(-50*C13))/(1-EXP(-50))) -> 0.22380268 | E13: =IFERROR( IF( NORMSDIST((NORMSINV($C13)-SQRT($D13)*E$9)/SQRT(1-$D13))<0.03%, 0.03%, NORMSDIST((NORMSINV($C13)-SQRT($D13)*E$9)/SQRT(1-$D13)) ), 0.03% ) -> 0.0003 | F13: =IFERROR( IF( NORMSDIST((NORMSINV($C13)-SQRT($D13)*F$9)/SQRT(1-$D13))<0.03%, 0.03%, NORMSDIST((NORMSINV($C13)-SQRT($D13)*F$9)/SQRT(1-$D13)) ), 0.03% ) -> 0.0003 | G13: =IFERROR( IF( NORMSDIST((NORMSINV($C13)-SQRT($D13)*G$9)/SQRT(1-$D13))<0.03%, 0.03%, NORMSDIST((NORMSINV($C13)-SQRT($D13)*G$9)/SQRT(1-$D13)) ), 0.03% ) -> 0.0003 | H13: =IFERROR( IF( NORMSDIST((NORMSINV($C13)-SQRT($D13)*H$9)/SQRT(1-$D13))<0.03%, 0.03%, NORMSDIST((NORMSINV($C13)-SQRT($D13)*H$9)/SQRT(1-$D13)) ), 0.03% ) -> 0.0003 | I13: =IFERROR( IF( NORMSDIST((NORMSINV($C13)-SQRT($D13)*I$9)/SQRT(1-$D13))<0.03%, 0.03%, NORMSDIST((NORMSINV($C13)-SQRT($D13)*I$9)/SQRT(1-$D13)) ), 0.03% ) -> 0.0003 | J13: =IFERROR( IF( NORMSDIST((NORMSINV($C13)-SQRT($D13)*J$9)/SQRT(1-$D13))<0.03%, 0.03%, NORMSDIST((NORMSINV($C13)-SQRT($D13)*J$9)/SQRT(1-$D13)) ), 0.03% ) -> 0.0003
B14: ='TTC PD'!C12 -> A+ | C14: ='TTC PD'!D12 -> 0.0066 | D14: =(0.12*(1-EXP(-50*C14))/(1-EXP(-50)))+0.24*(1-(1-EXP(-50*C14))/(1-EXP(-50))) -> 0.20627085 | E14: =IFERROR( IF( NORMSDIST((NORMSINV($C14)-SQRT($D14)*E$9)/SQRT(1-$D14))<0.03%, 0.03%, NORMSDIST((NORMSINV($C14)-SQRT($D14)*E$9)/SQRT(1-$D14)) ), 0.03% ) -> 0.00068917818 | F14: =IFERROR( IF( NORMSDIST((NORMSINV($C14)-SQRT($D14)*F$9)/SQRT(1-$D14))<0.03%, 0.03%, NORMSDIST((NORMSINV($C14)-SQRT($D14)*F$9)/SQRT(1-$D14)) ), 0.03% ) -> 0.00037879399 | G14: =IFERROR( IF( NORMSDIST((NORMSINV($C14)-SQRT($D14)*G$9)/SQRT(1-$D14))<0.03%, 0.03%, NORMSDIST((NORMSINV($C14)-SQRT($D14)*G$9)/SQRT(1-$D14)) ), 0.03% ) -> 0.0003 | H14: =IFERROR( IF( NORMSDIST((NORMSINV($C14)-SQRT($D14)*H$9)/SQRT(1-$D14))<0.03%, 0.03%, NORMSDIST((NORMSINV($C14)-SQRT($D14)*H$9)/SQRT(1-$D14)) ), 0.03% ) -> 0.0003 | I14: =IFERROR( IF( NORMSDIST((NORMSINV($C14)-SQRT($D14)*I$9)/SQRT(1-$D14))<0.03%, 0.03%, NORMSDIST((NORMSINV($C14)-SQRT($D14)*I$9)/SQRT(1-$D14)) ), 0.03% ) -> 0.0003 | J14: =IFERROR( IF( NORMSDIST((NORMSINV($C14)-SQRT($D14)*J$9)/SQRT(1-$D14))<0.03%, 0.03%, NORMSDIST((NORMSINV($C14)-SQRT($D14)*J$9)/SQRT(1-$D14)) ), 0.03% ) -> 0.0003
B15: ='TTC PD'!C13 -> A | C15: ='TTC PD'!D13 -> 0.0066 | D15: =(0.12*(1-EXP(-50*C15))/(1-EXP(-50)))+0.24*(1-(1-EXP(-50*C15))/(1-EXP(-50))) -> 0.20627085 | E15: =IFERROR( IF( NORMSDIST((NORMSINV($C15)-SQRT($D15)*E$9)/SQRT(1-$D15))<0.03%, 0.03%, NORMSDIST((NORMSINV($C15)-SQRT($D15)*E$9)/SQRT(1-$D15)) ), 0.03% ) -> 0.00068917818 | F15: =IFERROR( IF( NORMSDIST((NORMSINV($C15)-SQRT($D15)*F$9)/SQRT(1-$D15))<0.03%, 0.03%, NORMSDIST((NORMSINV($C15)-SQRT($D15)*F$9)/SQRT(1-$D15)) ), 0.03% ) -> 0.00037879399 | G15: =IFERROR( IF( NORMSDIST((NORMSINV($C15)-SQRT($D15)*G$9)/SQRT(1-$D15))<0.03%, 0.03%, NORMSDIST((NORMSINV($C15)-SQRT($D15)*G$9)/SQRT(1-$D15)) ), 0.03% ) -> 0.0003 | H15: =IFERROR( IF( NORMSDIST((NORMSINV($C15)-SQRT($D15)*H$9)/SQRT(1-$D15))<0.03%, 0.03%, NORMSDIST((NORMSINV($C15)-SQRT($D15)*H$9)/SQRT(1-$D15)) ), 0.03% ) -> 0.0003 | I15: =IFERROR( IF( NORMSDIST((NORMSINV($C15)-SQRT($D15)*I$9)/SQRT(1-$D15))<0.03%, 0.03%, NORMSDIST((NORMSINV($C15)-SQRT($D15)*I$9)/SQRT(1-$D15)) ), 0.03% ) -> 0.0003 | J15: =IFERROR( IF( NORMSDIST((NORMSINV($C15)-SQRT($D15)*J$9)/SQRT(1-$D15))<0.03%, 0.03%, NORMSDIST((NORMSINV($C15)-SQRT($D15)*J$9)/SQRT(1-$D15)) ), 0.03% ) -> 0.0003
B16: ='TTC PD'!C14 -> A- | C16: ='TTC PD'!D14 -> 0.0066 | D16: =(0.12*(1-EXP(-50*C16))/(1-EXP(-50)))+0.24*(1-(1-EXP(-50*C16))/(1-EXP(-50))) -> 0.20627085 | E16: =IFERROR( IF( NORMSDIST((NORMSINV($C16)-SQRT($D16)*E$9)/SQRT(1-$D16))<0.03%, 0.03%, NORMSDIST((NORMSINV($C16)-SQRT($D16)*E$9)/SQRT(1-$D16)) ), 0.03% ) -> 0.00068917818 | F16: =IFERROR( IF( NORMSDIST((NORMSINV($C16)-SQRT($D16)*F$9)/SQRT(1-$D16))<0.03%, 0.03%, NORMSDIST((NORMSINV($C16)-SQRT($D16)*F$9)/SQRT(1-$D16)) ), 0.03% ) -> 0.00037879399 | G16: =IFERROR( IF( NORMSDIST((NORMSINV($C16)-SQRT($D16)*G$9)/SQRT(1-$D16))<0.03%, 0.03%, NORMSDIST((NORMSINV($C16)-SQRT($D16)*G$9)/SQRT(1-$D16)) ), 0.03% ) -> 0.0003 | H16: =IFERROR( IF( NORMSDIST((NORMSINV($C16)-SQRT($D16)*H$9)/SQRT(1-$D16))<0.03%, 0.03%, NORMSDIST((NORMSINV($C16)-SQRT($D16)*H$9)/SQRT(1-$D16)) ), 0.03% ) -> 0.0003 | I16: =IFERROR( IF( NORMSDIST((NORMSINV($C16)-SQRT($D16)*I$9)/SQRT(1-$D16))<0.03%, 0.03%, NORMSDIST((NORMSINV($C16)-SQRT($D16)*I$9)/SQRT(1-$D16)) ), 0.03% ) -> 0.0003 | J16: =IFERROR( IF( NORMSDIST((NORMSINV($C16)-SQRT($D16)*J$9)/SQRT(1-$D16))<0.03%, 0.03%, NORMSDIST((NORMSINV($C16)-SQRT($D16)*J$9)/SQRT(1-$D16)) ), 0.03% ) -> 0.0003
B17: ='TTC PD'!C15 -> BBB+ | C17: ='TTC PD'!D15 -> 0.0221 | D17: =(0.12*(1-EXP(-50*C17))/(1-EXP(-50)))+0.24*(1-(1-EXP(-50*C17))/(1-EXP(-50))) -> 0.15974531 | E17: =IFERROR( IF( NORMSDIST((NORMSINV($C17)-SQRT($D17)*E$9)/SQRT(1-$D17))<0.03%, 0.03%, NORMSDIST((NORMSINV($C17)-SQRT($D17)*E$9)/SQRT(1-$D17)) ), 0.03% ) -> 0.005353392 | F17: =IFERROR( IF( NORMSDIST((NORMSINV($C17)-SQRT($D17)*F$9)/SQRT(1-$D17))<0.03%, 0.03%, NORMSDIST((NORMSINV($C17)-SQRT($D17)*F$9)/SQRT(1-$D17)) ), 0.03% ) -> 0.003504513 | G17: =IFERROR( IF( NORMSDIST((NORMSINV($C17)-SQRT($D17)*G$9)/SQRT(1-$D17))<0.03%, 0.03%, NORMSDIST((NORMSINV($C17)-SQRT($D17)*G$9)/SQRT(1-$D17)) ), 0.03% ) -> 0.0021673403 | H17: =IFERROR( IF( NORMSDIST((NORMSINV($C17)-SQRT($D17)*H$9)/SQRT(1-$D17))<0.03%, 0.03%, NORMSDIST((NORMSINV($C17)-SQRT($D17)*H$9)/SQRT(1-$D17)) ), 0.03% ) -> 0.0012239835 | I17: =IFERROR( IF( NORMSDIST((NORMSINV($C17)-SQRT($D17)*I$9)/SQRT(1-$D17))<0.03%, 0.03%, NORMSDIST((NORMSINV($C17)-SQRT($D17)*I$9)/SQRT(1-$D17)) ), 0.03% ) -> 0.00062999172 | J17: =IFERROR( IF( NORMSDIST((NORMSINV($C17)-SQRT($D17)*J$9)/SQRT(1-$D17))<0.03%, 0.03%, NORMSDIST((NORMSINV($C17)-SQRT($D17)*J$9)/SQRT(1-$D17)) ), 0.03% ) -> 0.0003
B18: ='TTC PD'!C16 -> BBB | C18: ='TTC PD'!D16 -> 0.0221 | D18: =(0.12*(1-EXP(-50*C18))/(1-EXP(-50)))+0.24*(1-(1-EXP(-50*C18))/(1-EXP(-50))) -> 0.15974531 | E18: =IFERROR( IF( NORMSDIST((NORMSINV($C18)-SQRT($D18)*E$9)/SQRT(1-$D18))<0.03%, 0.03%, NORMSDIST((NORMSINV($C18)-SQRT($D18)*E$9)/SQRT(1-$D18)) ), 0.03% ) -> 0.005353392 | F18: =IFERROR( IF( NORMSDIST((NORMSINV($C18)-SQRT($D18)*F$9)/SQRT(1-$D18))<0.03%, 0.03%, NORMSDIST((NORMSINV($C18)-SQRT($D18)*F$9)/SQRT(1-$D18)) ), 0.03% ) -> 0.003504513 | G18: =IFERROR( IF( NORMSDIST((NORMSINV($C18)-SQRT($D18)*G$9)/SQRT(1-$D18))<0.03%, 0.03%, NORMSDIST((NORMSINV($C18)-SQRT($D18)*G$9)/SQRT(1-$D18)) ), 0.03% ) -> 0.0021673403 | H18: =IFERROR( IF( NORMSDIST((NORMSINV($C18)-SQRT($D18)*H$9)/SQRT(1-$D18))<0.03%, 0.03%, NORMSDIST((NORMSINV($C18)-SQRT($D18)*H$9)/SQRT(1-$D18)) ), 0.03% ) -> 0.0012239835 | I18: =IFERROR( IF( NORMSDIST((NORMSINV($C18)-SQRT($D18)*I$9)/SQRT(1-$D18))<0.03%, 0.03%, NORMSDIST((NORMSINV($C18)-SQRT($D18)*I$9)/SQRT(1-$D18)) ), 0.03% ) -> 0.00062999172 | J18: =IFERROR( IF( NORMSDIST((NORMSINV($C18)-SQRT($D18)*J$9)/SQRT(1-$D18))<0.03%, 0.03%, NORMSDIST((NORMSINV($C18)-SQRT($D18)*J$9)/SQRT(1-$D18)) ), 0.03% ) -> 0.0003
B19: ='TTC PD'!C17 -> BBB- | C19: ='TTC PD'!D17 -> 0.0221 | D19: =(0.12*(1-EXP(-50*C19))/(1-EXP(-50)))+0.24*(1-(1-EXP(-50*C19))/(1-EXP(-50))) -> 0.15974531 | E19: =IFERROR( IF( NORMSDIST((NORMSINV($C19)-SQRT($D19)*E$9)/SQRT(1-$D19))<0.03%, 0.03%, NORMSDIST((NORMSINV($C19)-SQRT($D19)*E$9)/SQRT(1-$D19)) ), 0.03% ) -> 0.005353392 | F19: =IFERROR( IF( NORMSDIST((NORMSINV($C19)-SQRT($D19)*F$9)/SQRT(1-$D19))<0.03%, 0.03%, NORMSDIST((NORMSINV($C19)-SQRT($D19)*F$9)/SQRT(1-$D19)) ), 0.03% ) -> 0.003504513 | G19: =IFERROR( IF( NORMSDIST((NORMSINV($C19)-SQRT($D19)*G$9)/SQRT(1-$D19))<0.03%, 0.03%, NORMSDIST((NORMSINV($C19)-SQRT($D19)*G$9)/SQRT(1-$D19)) ), 0.03% ) -> 0.0021673403 | H19: =IFERROR( IF( NORMSDIST((NORMSINV($C19)-SQRT($D19)*H$9)/SQRT(1-$D19))<0.03%, 0.03%, NORMSDIST((NORMSINV($C19)-SQRT($D19)*H$9)/SQRT(1-$D19)) ), 0.03% ) -> 0.0012239835 | I19: =IFERROR( IF( NORMSDIST((NORMSINV($C19)-SQRT($D19)*I$9)/SQRT(1-$D19))<0.03%, 0.03%, NORMSDIST((NORMSINV($C19)-SQRT($D19)*I$9)/SQRT(1-$D19)) ), 0.03% ) -> 0.00062999172 | J19: =IFERROR( IF( NORMSDIST((NORMSINV($C19)-SQRT($D19)*J$9)/SQRT(1-$D19))<0.03%, 0.03%, NORMSDIST((NORMSINV($C19)-SQRT($D19)*J$9)/SQRT(1-$D19)) ), 0.03% ) -> 0.0003
B20: ='TTC PD'!C18 -> BB+ | C20: ='TTC PD'!D18 -> 0.0992 | D20: =(0.12*(1-EXP(-50*C20))/(1-EXP(-50)))+0.24*(1-(1-EXP(-50*C20))/(1-EXP(-50))) -> 0.12084155 | E20: =IFERROR( IF( NORMSDIST((NORMSINV($C20)-SQRT($D20)*E$9)/SQRT(1-$D20))<0.03%, 0.03%, NORMSDIST((NORMSINV($C20)-SQRT($D20)*E$9)/SQRT(1-$D20)) ), 0.03% ) -> 0.046947093 | F20: =IFERROR( IF( NORMSDIST((NORMSINV($C20)-SQRT($D20)*F$9)/SQRT(1-$D20))<0.03%, 0.03%, NORMSDIST((NORMSINV($C20)-SQRT($D20)*F$9)/SQRT(1-$D20)) ), 0.03% ) -> 0.036097097 | G20: =IFERROR( IF( NORMSDIST((NORMSINV($C20)-SQRT($D20)*G$9)/SQRT(1-$D20))<0.03%, 0.03%, NORMSDIST((NORMSINV($C20)-SQRT($D20)*G$9)/SQRT(1-$D20)) ), 0.03% ) -> 0.026754164 | H20: =IFERROR( IF( NORMSDIST((NORMSINV($C20)-SQRT($D20)*H$9)/SQRT(1-$D20))<0.03%, 0.03%, NORMSDIST((NORMSINV($C20)-SQRT($D20)*H$9)/SQRT(1-$D20)) ), 0.03% ) -> 0.018704154 | I20: =IFERROR( IF( NORMSDIST((NORMSINV($C20)-SQRT($D20)*I$9)/SQRT(1-$D20))<0.03%, 0.03%, NORMSDIST((NORMSINV($C20)-SQRT($D20)*I$9)/SQRT(1-$D20)) ), 0.03% ) -> 0.012310709 | J20: =IFERROR( IF( NORMSDIST((NORMSINV($C20)-SQRT($D20)*J$9)/SQRT(1-$D20))<0.03%, 0.03%, NORMSDIST((NORMSINV($C20)-SQRT($D20)*J$9)/SQRT(1-$D20)) ), 0.03% ) -> 0.0074718577
B21: ='TTC PD'!C19 -> Unrated | C21: ='TTC PD'!D19 -> 0.0992 | D21: =(0.12*(1-EXP(-50*C21))/(1-EXP(-50)))+0.24*(1-(1-EXP(-50*C21))/(1-EXP(-50))) -> 0.12084155 | E21: =IFERROR( IF( NORMSDIST((NORMSINV($C21)-SQRT($D21)*E$9)/SQRT(1-$D21))<0.03%, 0.03%, NORMSDIST((NORMSINV($C21)-SQRT($D21)*E$9)/SQRT(1-$D21)) ), 0.03% ) -> 0.046947093 | F21: =IFERROR( IF( NORMSDIST((NORMSINV($C21)-SQRT($D21)*F$9)/SQRT(1-$D21))<0.03%, 0.03%, NORMSDIST((NORMSINV($C21)-SQRT($D21)*F$9)/SQRT(1-$D21)) ), 0.03% ) -> 0.036097097 | G21: =IFERROR( IF( NORMSDIST((NORMSINV($C21)-SQRT($D21)*G$9)/SQRT(1-$D21))<0.03%, 0.03%, NORMSDIST((NORMSINV($C21)-SQRT($D21)*G$9)/SQRT(1-$D21)) ), 0.03% ) -> 0.026754164 | H21: =IFERROR( IF( NORMSDIST((NORMSINV($C21)-SQRT($D21)*H$9)/SQRT(1-$D21))<0.03%, 0.03%, NORMSDIST((NORMSINV($C21)-SQRT($D21)*H$9)/SQRT(1-$D21)) ), 0.03% ) -> 0.018704154 | I21: =IFERROR( IF( NORMSDIST((NORMSINV($C21)-SQRT($D21)*I$9)/SQRT(1-$D21))<0.03%, 0.03%, NORMSDIST((NORMSINV($C21)-SQRT($D21)*I$9)/SQRT(1-$D21)) ), 0.03% ) -> 0.012310709 | J21: =IFERROR( IF( NORMSDIST((NORMSINV($C21)-SQRT($D21)*J$9)/SQRT(1-$D21))<0.03%, 0.03%, NORMSDIST((NORMSINV($C21)-SQRT($D21)*J$9)/SQRT(1-$D21)) ), 0.03% ) -> 0.0074718577
B23: Upturn | E23: 2026 | F23: =E23+1 -> 2027 | G23: =F23+1 -> 2028 | H23: =G23+1 -> 2029 | I23: =H23+1 -> 2030 | J23: =I23+1 -> 2031
B24: Grades | C24: TTC | D24: Asset Correlation | E24: ='MEV Scenario'!H16 -> 0.9005924 | F24: ='MEV Scenario'!I16 -> 1.2646064 | G24: ='MEV Scenario'!J16 -> 1.6589334 | H24: ='MEV Scenario'!K16 -> 2.1054203 | I24: ='MEV Scenario'!L16 -> 2.5979772 | J24: ='MEV Scenario'!M16 -> 3.1511719
B25: =B10 -> AAA | C25: =C10 -> 0.0003 | D25: =(0.12*(1-EXP(-50*C25))/(1-EXP(-50)))+0.24*(1-(1-EXP(-50*C25))/(1-EXP(-50))) -> 0.23821343 | E25: =IFERROR( IF( NORMSDIST((NORMSINV($C25)-SQRT($D25)*E$24)/SQRT(1-$D25))<0.03%, 0.03%, NORMSDIST((NORMSINV($C25)-SQRT($D25)*E$24)/SQRT(1-$D25)) ), 0.03% ) -> 0.0003 | F25: =IFERROR( IF( NORMSDIST((NORMSINV($C25)-SQRT($D25)*F$24)/SQRT(1-$D25))<0.03%, 0.03%, NORMSDIST((NORMSINV($C25)-SQRT($D25)*F$24)/SQRT(1-$D25)) ), 0.03% ) -> 0.0003 | G25: =IFERROR( IF( NORMSDIST((NORMSINV($C25)-SQRT($D25)*G$24)/SQRT(1-$D25))<0.03%, 0.03%, NORMSDIST((NORMSINV($C25)-SQRT($D25)*G$24)/SQRT(1-$D25)) ), 0.03% ) -> 0.0003 | H25: =IFERROR( IF( NORMSDIST((NORMSINV($C25)-SQRT($D25)*H$24)/SQRT(1-$D25))<0.03%, 0.03%, NORMSDIST((NORMSINV($C25)-SQRT($D25)*H$24)/SQRT(1-$D25)) ), 0.03% ) -> 0.0003 | I25: =IFERROR( IF( NORMSDIST((NORMSINV($C25)-SQRT($D25)*I$24)/SQRT(1-$D25))<0.03%, 0.03%, NORMSDIST((NORMSINV($C25)-SQRT($D25)*I$24)/SQRT(1-$D25)) ), 0.03% ) -> 0.0003 | J25: =IFERROR( IF( NORMSDIST((NORMSINV($C25)-SQRT($D25)*J$24)/SQRT(1-$D25))<0.03%, 0.03%, NORMSDIST((NORMSINV($C25)-SQRT($D25)*J$24)/SQRT(1-$D25)) ), 0.03% ) -> 0.0003
B26: =B11 -> AA+ | C26: =C11 -> 0.0029 | D26: =(0.12*(1-EXP(-50*C26))/(1-EXP(-50)))+0.24*(1-(1-EXP(-50*C26))/(1-EXP(-50))) -> 0.22380268 | E26: =IFERROR( IF( NORMSDIST((NORMSINV($C26)-SQRT($D26)*E$24)/SQRT(1-$D26))<0.03%, 0.03%, NORMSDIST((NORMSINV($C26)-SQRT($D26)*E$24)/SQRT(1-$D26)) ), 0.03% ) -> 0.0003 | F26: =IFERROR( IF( NORMSDIST((NORMSINV($C26)-SQRT($D26)*F$24)/SQRT(1-$D26))<0.03%, 0.03%, NORMSDIST((NORMSINV($C26)-SQRT($D26)*F$24)/SQRT(1-$D26)) ), 0.03% ) -> 0.0003 | G26: =IFERROR( IF( NORMSDIST((NORMSINV($C26)-SQRT($D26)*G$24)/SQRT(1-$D26))<0.03%, 0.03%, NORMSDIST((NORMSINV($C26)-SQRT($D26)*G$24)/SQRT(1-$D26)) ), 0.03% ) -> 0.0003 | H26: =IFERROR( IF( NORMSDIST((NORMSINV($C26)-SQRT($D26)*H$24)/SQRT(1-$D26))<0.03%, 0.03%, NORMSDIST((NORMSINV($C26)-SQRT($D26)*H$24)/SQRT(1-$D26)) ), 0.03% ) -> 0.0003 | I26: =IFERROR( IF( NORMSDIST((NORMSINV($C26)-SQRT($D26)*I$24)/SQRT(1-$D26))<0.03%, 0.03%, NORMSDIST((NORMSINV($C26)-SQRT($D26)*I$24)/SQRT(1-$D26)) ), 0.03% ) -> 0.0003 | J26: =IFERROR( IF( NORMSDIST((NORMSINV($C26)-SQRT($D26)*J$24)/SQRT(1-$D26))<0.03%, 0.03%, NORMSDIST((NORMSINV($C26)-SQRT($D26)*J$24)/SQRT(1-$D26)) ), 0.03% ) -> 0.0003
B27: =B12 -> AA | C27: =C12 -> 0.0029 | D27: =(0.12*(1-EXP(-50*C27))/(1-EXP(-50)))+0.24*(1-(1-EXP(-50*C27))/(1-EXP(-50))) -> 0.22380268 | E27: =IFERROR( IF( NORMSDIST((NORMSINV($C27)-SQRT($D27)*E$24)/SQRT(1-$D27))<0.03%, 0.03%, NORMSDIST((NORMSINV($C27)-SQRT($D27)*E$24)/SQRT(1-$D27)) ), 0.03% ) -> 0.0003 | F27: =IFERROR( IF( NORMSDIST((NORMSINV($C27)-SQRT($D27)*F$24)/SQRT(1-$D27))<0.03%, 0.03%, NORMSDIST((NORMSINV($C27)-SQRT($D27)*F$24)/SQRT(1-$D27)) ), 0.03% ) -> 0.0003 | G27: =IFERROR( IF( NORMSDIST((NORMSINV($C27)-SQRT($D27)*G$24)/SQRT(1-$D27))<0.03%, 0.03%, NORMSDIST((NORMSINV($C27)-SQRT($D27)*G$24)/SQRT(1-$D27)) ), 0.03% ) -> 0.0003 | H27: =IFERROR( IF( NORMSDIST((NORMSINV($C27)-SQRT($D27)*H$24)/SQRT(1-$D27))<0.03%, 0.03%, NORMSDIST((NORMSINV($C27)-SQRT($D27)*H$24)/SQRT(1-$D27)) ), 0.03% ) -> 0.0003 | I27: =IFERROR( IF( NORMSDIST((NORMSINV($C27)-SQRT($D27)*I$24)/SQRT(1-$D27))<0.03%, 0.03%, NORMSDIST((NORMSINV($C27)-SQRT($D27)*I$24)/SQRT(1-$D27)) ), 0.03% ) -> 0.0003 | J27: =IFERROR( IF( NORMSDIST((NORMSINV($C27)-SQRT($D27)*J$24)/SQRT(1-$D27))<0.03%, 0.03%, NORMSDIST((NORMSINV($C27)-SQRT($D27)*J$24)/SQRT(1-$D27)) ), 0.03% ) -> 0.0003
B28: =B13 -> AA- | C28: =C13 -> 0.0029 | D28: =(0.12*(1-EXP(-50*C28))/(1-EXP(-50)))+0.24*(1-(1-EXP(-50*C28))/(1-EXP(-50))) -> 0.22380268 | E28: =IFERROR( IF( NORMSDIST((NORMSINV($C28)-SQRT($D28)*E$24)/SQRT(1-$D28))<0.03%, 0.03%, NORMSDIST((NORMSINV($C28)-SQRT($D28)*E$24)/SQRT(1-$D28)) ), 0.03% ) -> 0.0003 | F28: =IFERROR( IF( NORMSDIST((NORMSINV($C28)-SQRT($D28)*F$24)/SQRT(1-$D28))<0.03%, 0.03%, NORMSDIST((NORMSINV($C28)-SQRT($D28)*F$24)/SQRT(1-$D28)) ), 0.03% ) -> 0.0003 | G28: =IFERROR( IF( NORMSDIST((NORMSINV($C28)-SQRT($D28)*G$24)/SQRT(1-$D28))<0.03%, 0.03%, NORMSDIST((NORMSINV($C28)-SQRT($D28)*G$24)/SQRT(1-$D28)) ), 0.03% ) -> 0.0003 | H28: =IFERROR( IF( NORMSDIST((NORMSINV($C28)-SQRT($D28)*H$24)/SQRT(1-$D28))<0.03%, 0.03%, NORMSDIST((NORMSINV($C28)-SQRT($D28)*H$24)/SQRT(1-$D28)) ), 0.03% ) -> 0.0003 | I28: =IFERROR( IF( NORMSDIST((NORMSINV($C28)-SQRT($D28)*I$24)/SQRT(1-$D28))<0.03%, 0.03%, NORMSDIST((NORMSINV($C28)-SQRT($D28)*I$24)/SQRT(1-$D28)) ), 0.03% ) -> 0.0003 | J28: =IFERROR( IF( NORMSDIST((NORMSINV($C28)-SQRT($D28)*J$24)/SQRT(1-$D28))<0.03%, 0.03%, NORMSDIST((NORMSINV($C28)-SQRT($D28)*J$24)/SQRT(1-$D28)) ), 0.03% ) -> 0.0003
B29: =B14 -> A+ | C29: =C14 -> 0.0066 | D29: =(0.12*(1-EXP(-50*C29))/(1-EXP(-50)))+0.24*(1-(1-EXP(-50*C29))/(1-EXP(-50))) -> 0.20627085 | E29: =IFERROR( IF( NORMSDIST((NORMSINV($C29)-SQRT($D29)*E$24)/SQRT(1-$D29))<0.03%, 0.03%, NORMSDIST((NORMSINV($C29)-SQRT($D29)*E$24)/SQRT(1-$D29)) ), 0.03% ) -> 0.00059580224 | F29: =IFERROR( IF( NORMSDIST((NORMSINV($C29)-SQRT($D29)*F$24)/SQRT(1-$D29))<0.03%, 0.03%, NORMSDIST((NORMSINV($C29)-SQRT($D29)*F$24)/SQRT(1-$D29)) ), 0.03% ) -> 0.00030576408 | G29: =IFERROR( IF( NORMSDIST((NORMSINV($C29)-SQRT($D29)*G$24)/SQRT(1-$D29))<0.03%, 0.03%, NORMSDIST((NORMSINV($C29)-SQRT($D29)*G$24)/SQRT(1-$D29)) ), 0.03% ) -> 0.0003 | H29: =IFERROR( IF( NORMSDIST((NORMSINV($C29)-SQRT($D29)*H$24)/SQRT(1-$D29))<0.03%, 0.03%, NORMSDIST((NORMSINV($C29)-SQRT($D29)*H$24)/SQRT(1-$D29)) ), 0.03% ) -> 0.0003 | I29: =IFERROR( IF( NORMSDIST((NORMSINV($C29)-SQRT($D29)*I$24)/SQRT(1-$D29))<0.03%, 0.03%, NORMSDIST((NORMSINV($C29)-SQRT($D29)*I$24)/SQRT(1-$D29)) ), 0.03% ) -> 0.0003 | J29: =IFERROR( IF( NORMSDIST((NORMSINV($C29)-SQRT($D29)*J$24)/SQRT(1-$D29))<0.03%, 0.03%, NORMSDIST((NORMSINV($C29)-SQRT($D29)*J$24)/SQRT(1-$D29)) ), 0.03% ) -> 0.0003
B30: =B15 -> A | C30: =C15 -> 0.0066 | D30: =(0.12*(1-EXP(-50*C30))/(1-EXP(-50)))+0.24*(1-(1-EXP(-50*C30))/(1-EXP(-50))) -> 0.20627085 | E30: =IFERROR( IF( NORMSDIST((NORMSINV($C30)-SQRT($D30)*E$24)/SQRT(1-$D30))<0.03%, 0.03%, NORMSDIST((NORMSINV($C30)-SQRT($D30)*E$24)/SQRT(1-$D30)) ), 0.03% ) -> 0.00059580224 | F30: =IFERROR( IF( NORMSDIST((NORMSINV($C30)-SQRT($D30)*F$24)/SQRT(1-$D30))<0.03%, 0.03%, NORMSDIST((NORMSINV($C30)-SQRT($D30)*F$24)/SQRT(1-$D30)) ), 0.03% ) -> 0.00030576408 | G30: =IFERROR( IF( NORMSDIST((NORMSINV($C30)-SQRT($D30)*G$24)/SQRT(1-$D30))<0.03%, 0.03%, NORMSDIST((NORMSINV($C30)-SQRT($D30)*G$24)/SQRT(1-$D30)) ), 0.03% ) -> 0.0003 | H30: =IFERROR( IF( NORMSDIST((NORMSINV($C30)-SQRT($D30)*H$24)/SQRT(1-$D30))<0.03%, 0.03%, NORMSDIST((NORMSINV($C30)-SQRT($D30)*H$24)/SQRT(1-$D30)) ), 0.03% ) -> 0.0003 | I30: =IFERROR( IF( NORMSDIST((NORMSINV($C30)-SQRT($D30)*I$24)/SQRT(1-$D30))<0.03%, 0.03%, NORMSDIST((NORMSINV($C30)-SQRT($D30)*I$24)/SQRT(1-$D30)) ), 0.03% ) -> 0.0003 | J30: =IFERROR( IF( NORMSDIST((NORMSINV($C30)-SQRT($D30)*J$24)/SQRT(1-$D30))<0.03%, 0.03%, NORMSDIST((NORMSINV($C30)-SQRT($D30)*J$24)/SQRT(1-$D30)) ), 0.03% ) -> 0.0003
B31: =B16 -> A- | C31: =C16 -> 0.0066 | D31: =(0.12*(1-EXP(-50*C31))/(1-EXP(-50)))+0.24*(1-(1-EXP(-50*C31))/(1-EXP(-50))) -> 0.20627085 | E31: =IFERROR( IF( NORMSDIST((NORMSINV($C31)-SQRT($D31)*E$24)/SQRT(1-$D31))<0.03%, 0.03%, NORMSDIST((NORMSINV($C31)-SQRT($D31)*E$24)/SQRT(1-$D31)) ), 0.03% ) -> 0.00059580224 | F31: =IFERROR( IF( NORMSDIST((NORMSINV($C31)-SQRT($D31)*F$24)/SQRT(1-$D31))<0.03%, 0.03%, NORMSDIST((NORMSINV($C31)-SQRT($D31)*F$24)/SQRT(1-$D31)) ), 0.03% ) -> 0.00030576408 | G31: =IFERROR( IF( NORMSDIST((NORMSINV($C31)-SQRT($D31)*G$24)/SQRT(1-$D31))<0.03%, 0.03%, NORMSDIST((NORMSINV($C31)-SQRT($D31)*G$24)/SQRT(1-$D31)) ), 0.03% ) -> 0.0003 | H31: =IFERROR( IF( NORMSDIST((NORMSINV($C31)-SQRT($D31)*H$24)/SQRT(1-$D31))<0.03%, 0.03%, NORMSDIST((NORMSINV($C31)-SQRT($D31)*H$24)/SQRT(1-$D31)) ), 0.03% ) -> 0.0003 | I31: =IFERROR( IF( NORMSDIST((NORMSINV($C31)-SQRT($D31)*I$24)/SQRT(1-$D31))<0.03%, 0.03%, NORMSDIST((NORMSINV($C31)-SQRT($D31)*I$24)/SQRT(1-$D31)) ), 0.03% ) -> 0.0003 | J31: =IFERROR( IF( NORMSDIST((NORMSINV($C31)-SQRT($D31)*J$24)/SQRT(1-$D31))<0.03%, 0.03%, NORMSDIST((NORMSINV($C31)-SQRT($D31)*J$24)/SQRT(1-$D31)) ), 0.03% ) -> 0.0003
B32: =B17 -> BBB+ | C32: =C17 -> 0.0221 | D32: =(0.12*(1-EXP(-50*C32))/(1-EXP(-50)))+0.24*(1-(1-EXP(-50*C32))/(1-EXP(-50))) -> 0.15974531 | E32: =IFERROR( IF( NORMSDIST((NORMSINV($C32)-SQRT($D32)*E$24)/SQRT(1-$D32))<0.03%, 0.03%, NORMSDIST((NORMSINV($C32)-SQRT($D32)*E$24)/SQRT(1-$D32)) ), 0.03% ) -> 0.0048292177 | F32: =IFERROR( IF( NORMSDIST((NORMSINV($C32)-SQRT($D32)*F$24)/SQRT(1-$D32))<0.03%, 0.03%, NORMSDIST((NORMSINV($C32)-SQRT($D32)*F$24)/SQRT(1-$D32)) ), 0.03% ) -> 0.0030113581 | G32: =IFERROR( IF( NORMSDIST((NORMSINV($C32)-SQRT($D32)*G$24)/SQRT(1-$D32))<0.03%, 0.03%, NORMSDIST((NORMSINV($C32)-SQRT($D32)*G$24)/SQRT(1-$D32)) ), 0.03% ) -> 0.0017587271 | H32: =IFERROR( IF( NORMSDIST((NORMSINV($C32)-SQRT($D32)*H$24)/SQRT(1-$D32))<0.03%, 0.03%, NORMSDIST((NORMSINV($C32)-SQRT($D32)*H$24)/SQRT(1-$D32)) ), 0.03% ) -> 0.0009254922 | I32: =IFERROR( IF( NORMSDIST((NORMSINV($C32)-SQRT($D32)*I$24)/SQRT(1-$D32))<0.03%, 0.03%, NORMSDIST((NORMSINV($C32)-SQRT($D32)*I$24)/SQRT(1-$D32)) ), 0.03% ) -> 0.00043748296 | J32: =IFERROR( IF( NORMSDIST((NORMSINV($C32)-SQRT($D32)*J$24)/SQRT(1-$D32))<0.03%, 0.03%, NORMSDIST((NORMSINV($C32)-SQRT($D32)*J$24)/SQRT(1-$D32)) ), 0.03% ) -> 0.0003
B33: =B18 -> BBB | C33: =C18 -> 0.0221 | D33: =(0.12*(1-EXP(-50*C33))/(1-EXP(-50)))+0.24*(1-(1-EXP(-50*C33))/(1-EXP(-50))) -> 0.15974531 | E33: =IFERROR( IF( NORMSDIST((NORMSINV($C33)-SQRT($D33)*E$24)/SQRT(1-$D33))<0.03%, 0.03%, NORMSDIST((NORMSINV($C33)-SQRT($D33)*E$24)/SQRT(1-$D33)) ), 0.03% ) -> 0.0048292177 | F33: =IFERROR( IF( NORMSDIST((NORMSINV($C33)-SQRT($D33)*F$24)/SQRT(1-$D33))<0.03%, 0.03%, NORMSDIST((NORMSINV($C33)-SQRT($D33)*F$24)/SQRT(1-$D33)) ), 0.03% ) -> 0.0030113581 | G33: =IFERROR( IF( NORMSDIST((NORMSINV($C33)-SQRT($D33)*G$24)/SQRT(1-$D33))<0.03%, 0.03%, NORMSDIST((NORMSINV($C33)-SQRT($D33)*G$24)/SQRT(1-$D33)) ), 0.03% ) -> 0.0017587271 | H33: =IFERROR( IF( NORMSDIST((NORMSINV($C33)-SQRT($D33)*H$24)/SQRT(1-$D33))<0.03%, 0.03%, NORMSDIST((NORMSINV($C33)-SQRT($D33)*H$24)/SQRT(1-$D33)) ), 0.03% ) -> 0.0009254922 | I33: =IFERROR( IF( NORMSDIST((NORMSINV($C33)-SQRT($D33)*I$24)/SQRT(1-$D33))<0.03%, 0.03%, NORMSDIST((NORMSINV($C33)-SQRT($D33)*I$24)/SQRT(1-$D33)) ), 0.03% ) -> 0.00043748296 | J33: =IFERROR( IF( NORMSDIST((NORMSINV($C33)-SQRT($D33)*J$24)/SQRT(1-$D33))<0.03%, 0.03%, NORMSDIST((NORMSINV($C33)-SQRT($D33)*J$24)/SQRT(1-$D33)) ), 0.03% ) -> 0.0003
B34: =B19 -> BBB- | C34: =C19 -> 0.0221 | D34: =(0.12*(1-EXP(-50*C34))/(1-EXP(-50)))+0.24*(1-(1-EXP(-50*C34))/(1-EXP(-50))) -> 0.15974531 | E34: =IFERROR( IF( NORMSDIST((NORMSINV($C34)-SQRT($D34)*E$24)/SQRT(1-$D34))<0.03%, 0.03%, NORMSDIST((NORMSINV($C34)-SQRT($D34)*E$24)/SQRT(1-$D34)) ), 0.03% ) -> 0.0048292177 | F34: =IFERROR( IF( NORMSDIST((NORMSINV($C34)-SQRT($D34)*F$24)/SQRT(1-$D34))<0.03%, 0.03%, NORMSDIST((NORMSINV($C34)-SQRT($D34)*F$24)/SQRT(1-$D34)) ), 0.03% ) -> 0.0030113581 | G34: =IFERROR( IF( NORMSDIST((NORMSINV($C34)-SQRT($D34)*G$24)/SQRT(1-$D34))<0.03%, 0.03%, NORMSDIST((NORMSINV($C34)-SQRT($D34)*G$24)/SQRT(1-$D34)) ), 0.03% ) -> 0.0017587271 | H34: =IFERROR( IF( NORMSDIST((NORMSINV($C34)-SQRT($D34)*H$24)/SQRT(1-$D34))<0.03%, 0.03%, NORMSDIST((NORMSINV($C34)-SQRT($D34)*H$24)/SQRT(1-$D34)) ), 0.03% ) -> 0.0009254922 | I34: =IFERROR( IF( NORMSDIST((NORMSINV($C34)-SQRT($D34)*I$24)/SQRT(1-$D34))<0.03%, 0.03%, NORMSDIST((NORMSINV($C34)-SQRT($D34)*I$24)/SQRT(1-$D34)) ), 0.03% ) -> 0.00043748296 | J34: =IFERROR( IF( NORMSDIST((NORMSINV($C34)-SQRT($D34)*J$24)/SQRT(1-$D34))<0.03%, 0.03%, NORMSDIST((NORMSINV($C34)-SQRT($D34)*J$24)/SQRT(1-$D34)) ), 0.03% ) -> 0.0003
B35: =B20 -> BB+ | C35: =C20 -> 0.0992 | D35: =(0.12*(1-EXP(-50*C35))/(1-EXP(-50)))+0.24*(1-(1-EXP(-50*C35))/(1-EXP(-50))) -> 0.12084155 | E35: =IFERROR( IF( NORMSDIST((NORMSINV($C35)-SQRT($D35)*E$24)/SQRT(1-$D35))<0.03%, 0.03%, NORMSDIST((NORMSINV($C35)-SQRT($D35)*E$24)/SQRT(1-$D35)) ), 0.03% ) -> 0.044045227 | F35: =IFERROR( IF( NORMSDIST((NORMSINV($C35)-SQRT($D35)*F$24)/SQRT(1-$D35))<0.03%, 0.03%, NORMSDIST((NORMSINV($C35)-SQRT($D35)*F$24)/SQRT(1-$D35)) ), 0.03% ) -> 0.032846413 | G35: =IFERROR( IF( NORMSDIST((NORMSINV($C35)-SQRT($D35)*G$24)/SQRT(1-$D35))<0.03%, 0.03%, NORMSDIST((NORMSINV($C35)-SQRT($D35)*G$24)/SQRT(1-$D35)) ), 0.03% ) -> 0.023477361 | H35: =IFERROR( IF( NORMSDIST((NORMSINV($C35)-SQRT($D35)*H$24)/SQRT(1-$D35))<0.03%, 0.03%, NORMSDIST((NORMSINV($C35)-SQRT($D35)*H$24)/SQRT(1-$D35)) ), 0.03% ) -> 0.015689193 | I35: =IFERROR( IF( NORMSDIST((NORMSINV($C35)-SQRT($D35)*I$24)/SQRT(1-$D35))<0.03%, 0.03%, NORMSDIST((NORMSINV($C35)-SQRT($D35)*I$24)/SQRT(1-$D35)) ), 0.03% ) -> 0.0097755354 | J35: =IFERROR( IF( NORMSDIST((NORMSINV($C35)-SQRT($D35)*J$24)/SQRT(1-$D35))<0.03%, 0.03%, NORMSDIST((NORMSINV($C35)-SQRT($D35)*J$24)/SQRT(1-$D35)) ), 0.03% ) -> 0.0055434565
B36: =B21 -> Unrated | C36: =C21 -> 0.0992 | D36: =(0.12*(1-EXP(-50*C36))/(1-EXP(-50)))+0.24*(1-(1-EXP(-50*C36))/(1-EXP(-50))) -> 0.12084155 | E36: =IFERROR( IF( NORMSDIST((NORMSINV($C36)-SQRT($D36)*E$24)/SQRT(1-$D36))<0.03%, 0.03%, NORMSDIST((NORMSINV($C36)-SQRT($D36)*E$24)/SQRT(1-$D36)) ), 0.03% ) -> 0.044045227 | F36: =IFERROR( IF( NORMSDIST((NORMSINV($C36)-SQRT($D36)*F$24)/SQRT(1-$D36))<0.03%, 0.03%, NORMSDIST((NORMSINV($C36)-SQRT($D36)*F$24)/SQRT(1-$D36)) ), 0.03% ) -> 0.032846413 | G36: =IFERROR( IF( NORMSDIST((NORMSINV($C36)-SQRT($D36)*G$24)/SQRT(1-$D36))<0.03%, 0.03%, NORMSDIST((NORMSINV($C36)-SQRT($D36)*G$24)/SQRT(1-$D36)) ), 0.03% ) -> 0.023477361 | H36: =IFERROR( IF( NORMSDIST((NORMSINV($C36)-SQRT($D36)*H$24)/SQRT(1-$D36))<0.03%, 0.03%, NORMSDIST((NORMSINV($C36)-SQRT($D36)*H$24)/SQRT(1-$D36)) ), 0.03% ) -> 0.015689193 | I36: =IFERROR( IF( NORMSDIST((NORMSINV($C36)-SQRT($D36)*I$24)/SQRT(1-$D36))<0.03%, 0.03%, NORMSDIST((NORMSINV($C36)-SQRT($D36)*I$24)/SQRT(1-$D36)) ), 0.03% ) -> 0.0097755354 | J36: =IFERROR( IF( NORMSDIST((NORMSINV($C36)-SQRT($D36)*J$24)/SQRT(1-$D36))<0.03%, 0.03%, NORMSDIST((NORMSINV($C36)-SQRT($D36)*J$24)/SQRT(1-$D36)) ), 0.03% ) -> 0.0055434565
B39: Downturn | E39: 2026 | F39: =E39+1 -> 2027 | G39: =F39+1 -> 2028 | H39: =G39+1 -> 2029 | I39: =H39+1 -> 2030 | J39: =I39+1 -> 2031
B40: Grades | C40: TTC | D40: Asset Correlation | E40: ='MEV Scenario'!H21 -> 0.73684832 | F40: ='MEV Scenario'!I21 -> 1.034678 | G40: ='MEV Scenario'!J21 -> 1.3573091 | H40: ='MEV Scenario'!K21 -> 1.7226166 | I40: ='MEV Scenario'!L21 -> 2.1256177 | J40: ='MEV Scenario'!M21 -> 2.5782316
B41: =B25 -> AAA | C41: =C10 -> 0.0003 | D41: =(0.12*(1-EXP(-50*C41))/(1-EXP(-50)))+0.24*(1-(1-EXP(-50*C41))/(1-EXP(-50))) -> 0.23821343 | E41: =IFERROR( IF( NORMSDIST((NORMSINV($C41)-SQRT($D41)*E$40)/SQRT(1-$D41))<0.03%, 0.03%, NORMSDIST((NORMSINV($C41)-SQRT($D41)*E$40)/SQRT(1-$D41)) ), 0.03% ) -> 0.0003 | F41: =IFERROR( IF( NORMSDIST((NORMSINV($C41)-SQRT($D41)*F$40)/SQRT(1-$D41))<0.03%, 0.03%, NORMSDIST((NORMSINV($C41)-SQRT($D41)*F$40)/SQRT(1-$D41)) ), 0.03% ) -> 0.0003 | G41: =IFERROR( IF( NORMSDIST((NORMSINV($C41)-SQRT($D41)*G$40)/SQRT(1-$D41))<0.03%, 0.03%, NORMSDIST((NORMSINV($C41)-SQRT($D41)*G$40)/SQRT(1-$D41)) ), 0.03% ) -> 0.0003 | H41: =IFERROR( IF( NORMSDIST((NORMSINV($C41)-SQRT($D41)*H$40)/SQRT(1-$D41))<0.03%, 0.03%, NORMSDIST((NORMSINV($C41)-SQRT($D41)*H$40)/SQRT(1-$D41)) ), 0.03% ) -> 0.0003 | I41: =IFERROR( IF( NORMSDIST((NORMSINV($C41)-SQRT($D41)*I$40)/SQRT(1-$D41))<0.03%, 0.03%, NORMSDIST((NORMSINV($C41)-SQRT($D41)*I$40)/SQRT(1-$D41)) ), 0.03% ) -> 0.0003 | J41: =IFERROR( IF( NORMSDIST((NORMSINV($C41)-SQRT($D41)*J$40)/SQRT(1-$D41))<0.03%, 0.03%, NORMSDIST((NORMSINV($C41)-SQRT($D41)*J$40)/SQRT(1-$D41)) ), 0.03% ) -> 0.0003
B42: =B26 -> AA+ | C42: =C11 -> 0.0029 | D42: =(0.12*(1-EXP(-50*C42))/(1-EXP(-50)))+0.24*(1-(1-EXP(-50*C42))/(1-EXP(-50))) -> 0.22380268 | E42: =IFERROR( IF( NORMSDIST((NORMSINV($C42)-SQRT($D42)*E$40)/SQRT(1-$D42))<0.03%, 0.03%, NORMSDIST((NORMSINV($C42)-SQRT($D42)*E$40)/SQRT(1-$D42)) ), 0.03% ) -> 0.0003 | F42: =IFERROR( IF( NORMSDIST((NORMSINV($C42)-SQRT($D42)*F$40)/SQRT(1-$D42))<0.03%, 0.03%, NORMSDIST((NORMSINV($C42)-SQRT($D42)*F$40)/SQRT(1-$D42)) ), 0.03% ) -> 0.0003 | G42: =IFERROR( IF( NORMSDIST((NORMSINV($C42)-SQRT($D42)*G$40)/SQRT(1-$D42))<0.03%, 0.03%, NORMSDIST((NORMSINV($C42)-SQRT($D42)*G$40)/SQRT(1-$D42)) ), 0.03% ) -> 0.0003 | H42: =IFERROR( IF( NORMSDIST((NORMSINV($C42)-SQRT($D42)*H$40)/SQRT(1-$D42))<0.03%, 0.03%, NORMSDIST((NORMSINV($C42)-SQRT($D42)*H$40)/SQRT(1-$D42)) ), 0.03% ) -> 0.0003 | I42: =IFERROR( IF( NORMSDIST((NORMSINV($C42)-SQRT($D42)*I$40)/SQRT(1-$D42))<0.03%, 0.03%, NORMSDIST((NORMSINV($C42)-SQRT($D42)*I$40)/SQRT(1-$D42)) ), 0.03% ) -> 0.0003 | J42: =IFERROR( IF( NORMSDIST((NORMSINV($C42)-SQRT($D42)*J$40)/SQRT(1-$D42))<0.03%, 0.03%, NORMSDIST((NORMSINV($C42)-SQRT($D42)*J$40)/SQRT(1-$D42)) ), 0.03% ) -> 0.0003
B43: =B27 -> AA | C43: =C12 -> 0.0029 | D43: =(0.12*(1-EXP(-50*C43))/(1-EXP(-50)))+0.24*(1-(1-EXP(-50*C43))/(1-EXP(-50))) -> 0.22380268 | E43: =IFERROR( IF( NORMSDIST((NORMSINV($C43)-SQRT($D43)*E$40)/SQRT(1-$D43))<0.03%, 0.03%, NORMSDIST((NORMSINV($C43)-SQRT($D43)*E$40)/SQRT(1-$D43)) ), 0.03% ) -> 0.0003 | F43: =IFERROR( IF( NORMSDIST((NORMSINV($C43)-SQRT($D43)*F$40)/SQRT(1-$D43))<0.03%, 0.03%, NORMSDIST((NORMSINV($C43)-SQRT($D43)*F$40)/SQRT(1-$D43)) ), 0.03% ) -> 0.0003 | G43: =IFERROR( IF( NORMSDIST((NORMSINV($C43)-SQRT($D43)*G$40)/SQRT(1-$D43))<0.03%, 0.03%, NORMSDIST((NORMSINV($C43)-SQRT($D43)*G$40)/SQRT(1-$D43)) ), 0.03% ) -> 0.0003 | H43: =IFERROR( IF( NORMSDIST((NORMSINV($C43)-SQRT($D43)*H$40)/SQRT(1-$D43))<0.03%, 0.03%, NORMSDIST((NORMSINV($C43)-SQRT($D43)*H$40)/SQRT(1-$D43)) ), 0.03% ) -> 0.0003 | I43: =IFERROR( IF( NORMSDIST((NORMSINV($C43)-SQRT($D43)*I$40)/SQRT(1-$D43))<0.03%, 0.03%, NORMSDIST((NORMSINV($C43)-SQRT($D43)*I$40)/SQRT(1-$D43)) ), 0.03% ) -> 0.0003 | J43: =IFERROR( IF( NORMSDIST((NORMSINV($C43)-SQRT($D43)*J$40)/SQRT(1-$D43))<0.03%, 0.03%, NORMSDIST((NORMSINV($C43)-SQRT($D43)*J$40)/SQRT(1-$D43)) ), 0.03% ) -> 0.0003
B44: =B28 -> AA- | C44: =C13 -> 0.0029 | D44: =(0.12*(1-EXP(-50*C44))/(1-EXP(-50)))+0.24*(1-(1-EXP(-50*C44))/(1-EXP(-50))) -> 0.22380268 | E44: =IFERROR( IF( NORMSDIST((NORMSINV($C44)-SQRT($D44)*E$40)/SQRT(1-$D44))<0.03%, 0.03%, NORMSDIST((NORMSINV($C44)-SQRT($D44)*E$40)/SQRT(1-$D44)) ), 0.03% ) -> 0.0003 | F44: =IFERROR( IF( NORMSDIST((NORMSINV($C44)-SQRT($D44)*F$40)/SQRT(1-$D44))<0.03%, 0.03%, NORMSDIST((NORMSINV($C44)-SQRT($D44)*F$40)/SQRT(1-$D44)) ), 0.03% ) -> 0.0003 | G44: =IFERROR( IF( NORMSDIST((NORMSINV($C44)-SQRT($D44)*G$40)/SQRT(1-$D44))<0.03%, 0.03%, NORMSDIST((NORMSINV($C44)-SQRT($D44)*G$40)/SQRT(1-$D44)) ), 0.03% ) -> 0.0003 | H44: =IFERROR( IF( NORMSDIST((NORMSINV($C44)-SQRT($D44)*H$40)/SQRT(1-$D44))<0.03%, 0.03%, NORMSDIST((NORMSINV($C44)-SQRT($D44)*H$40)/SQRT(1-$D44)) ), 0.03% ) -> 0.0003 | I44: =IFERROR( IF( NORMSDIST((NORMSINV($C44)-SQRT($D44)*I$40)/SQRT(1-$D44))<0.03%, 0.03%, NORMSDIST((NORMSINV($C44)-SQRT($D44)*I$40)/SQRT(1-$D44)) ), 0.03% ) -> 0.0003 | J44: =IFERROR( IF( NORMSDIST((NORMSINV($C44)-SQRT($D44)*J$40)/SQRT(1-$D44))<0.03%, 0.03%, NORMSDIST((NORMSINV($C44)-SQRT($D44)*J$40)/SQRT(1-$D44)) ), 0.03% ) -> 0.0003
B45: =B29 -> A+ | C45: =C14 -> 0.0066 | D45: =(0.12*(1-EXP(-50*C45))/(1-EXP(-50)))+0.24*(1-(1-EXP(-50*C45))/(1-EXP(-50))) -> 0.20627085 | E45: =IFERROR( IF( NORMSDIST((NORMSINV($C45)-SQRT($D45)*E$40)/SQRT(1-$D45))<0.03%, 0.03%, NORMSDIST((NORMSINV($C45)-SQRT($D45)*E$40)/SQRT(1-$D45)) ), 0.03% ) -> 0.00079589045 | F45: =IFERROR( IF( NORMSDIST((NORMSINV($C45)-SQRT($D45)*F$40)/SQRT(1-$D45))<0.03%, 0.03%, NORMSDIST((NORMSINV($C45)-SQRT($D45)*F$40)/SQRT(1-$D45)) ), 0.03% ) -> 0.00046775427 | G45: =IFERROR( IF( NORMSDIST((NORMSINV($C45)-SQRT($D45)*G$40)/SQRT(1-$D45))<0.03%, 0.03%, NORMSDIST((NORMSINV($C45)-SQRT($D45)*G$40)/SQRT(1-$D45)) ), 0.03% ) -> 0.0003 | H45: =IFERROR( IF( NORMSDIST((NORMSINV($C45)-SQRT($D45)*H$40)/SQRT(1-$D45))<0.03%, 0.03%, NORMSDIST((NORMSINV($C45)-SQRT($D45)*H$40)/SQRT(1-$D45)) ), 0.03% ) -> 0.0003 | I45: =IFERROR( IF( NORMSDIST((NORMSINV($C45)-SQRT($D45)*I$40)/SQRT(1-$D45))<0.03%, 0.03%, NORMSDIST((NORMSINV($C45)-SQRT($D45)*I$40)/SQRT(1-$D45)) ), 0.03% ) -> 0.0003 | J45: =IFERROR( IF( NORMSDIST((NORMSINV($C45)-SQRT($D45)*J$40)/SQRT(1-$D45))<0.03%, 0.03%, NORMSDIST((NORMSINV($C45)-SQRT($D45)*J$40)/SQRT(1-$D45)) ), 0.03% ) -> 0.0003
B46: =B30 -> A | C46: =C15 -> 0.0066 | D46: =(0.12*(1-EXP(-50*C46))/(1-EXP(-50)))+0.24*(1-(1-EXP(-50*C46))/(1-EXP(-50))) -> 0.20627085 | E46: =IFERROR( IF( NORMSDIST((NORMSINV($C46)-SQRT($D46)*E$40)/SQRT(1-$D46))<0.03%, 0.03%, NORMSDIST((NORMSINV($C46)-SQRT($D46)*E$40)/SQRT(1-$D46)) ), 0.03% ) -> 0.00079589045 | F46: =IFERROR( IF( NORMSDIST((NORMSINV($C46)-SQRT($D46)*F$40)/SQRT(1-$D46))<0.03%, 0.03%, NORMSDIST((NORMSINV($C46)-SQRT($D46)*F$40)/SQRT(1-$D46)) ), 0.03% ) -> 0.00046775427 | G46: =IFERROR( IF( NORMSDIST((NORMSINV($C46)-SQRT($D46)*G$40)/SQRT(1-$D46))<0.03%, 0.03%, NORMSDIST((NORMSINV($C46)-SQRT($D46)*G$40)/SQRT(1-$D46)) ), 0.03% ) -> 0.0003 | H46: =IFERROR( IF( NORMSDIST((NORMSINV($C46)-SQRT($D46)*H$40)/SQRT(1-$D46))<0.03%, 0.03%, NORMSDIST((NORMSINV($C46)-SQRT($D46)*H$40)/SQRT(1-$D46)) ), 0.03% ) -> 0.0003 | I46: =IFERROR( IF( NORMSDIST((NORMSINV($C46)-SQRT($D46)*I$40)/SQRT(1-$D46))<0.03%, 0.03%, NORMSDIST((NORMSINV($C46)-SQRT($D46)*I$40)/SQRT(1-$D46)) ), 0.03% ) -> 0.0003 | J46: =IFERROR( IF( NORMSDIST((NORMSINV($C46)-SQRT($D46)*J$40)/SQRT(1-$D46))<0.03%, 0.03%, NORMSDIST((NORMSINV($C46)-SQRT($D46)*J$40)/SQRT(1-$D46)) ), 0.03% ) -> 0.0003
B47: =B31 -> A- | C47: =C16 -> 0.0066 | D47: =(0.12*(1-EXP(-50*C47))/(1-EXP(-50)))+0.24*(1-(1-EXP(-50*C47))/(1-EXP(-50))) -> 0.20627085 | E47: =IFERROR( IF( NORMSDIST((NORMSINV($C47)-SQRT($D47)*E$40)/SQRT(1-$D47))<0.03%, 0.03%, NORMSDIST((NORMSINV($C47)-SQRT($D47)*E$40)/SQRT(1-$D47)) ), 0.03% ) -> 0.00079589045 | F47: =IFERROR( IF( NORMSDIST((NORMSINV($C47)-SQRT($D47)*F$40)/SQRT(1-$D47))<0.03%, 0.03%, NORMSDIST((NORMSINV($C47)-SQRT($D47)*F$40)/SQRT(1-$D47)) ), 0.03% ) -> 0.00046775427 | G47: =IFERROR( IF( NORMSDIST((NORMSINV($C47)-SQRT($D47)*G$40)/SQRT(1-$D47))<0.03%, 0.03%, NORMSDIST((NORMSINV($C47)-SQRT($D47)*G$40)/SQRT(1-$D47)) ), 0.03% ) -> 0.0003 | H47: =IFERROR( IF( NORMSDIST((NORMSINV($C47)-SQRT($D47)*H$40)/SQRT(1-$D47))<0.03%, 0.03%, NORMSDIST((NORMSINV($C47)-SQRT($D47)*H$40)/SQRT(1-$D47)) ), 0.03% ) -> 0.0003 | I47: =IFERROR( IF( NORMSDIST((NORMSINV($C47)-SQRT($D47)*I$40)/SQRT(1-$D47))<0.03%, 0.03%, NORMSDIST((NORMSINV($C47)-SQRT($D47)*I$40)/SQRT(1-$D47)) ), 0.03% ) -> 0.0003 | J47: =IFERROR( IF( NORMSDIST((NORMSINV($C47)-SQRT($D47)*J$40)/SQRT(1-$D47))<0.03%, 0.03%, NORMSDIST((NORMSINV($C47)-SQRT($D47)*J$40)/SQRT(1-$D47)) ), 0.03% ) -> 0.0003
B48: =B32 -> BBB+ | C48: =C17 -> 0.0221 | D48: =(0.12*(1-EXP(-50*C48))/(1-EXP(-50)))+0.24*(1-(1-EXP(-50*C48))/(1-EXP(-50))) -> 0.15974531 | E48: =IFERROR( IF( NORMSDIST((NORMSINV($C48)-SQRT($D48)*E$40)/SQRT(1-$D48))<0.03%, 0.03%, NORMSDIST((NORMSINV($C48)-SQRT($D48)*E$40)/SQRT(1-$D48)) ), 0.03% ) -> 0.0059275591 | F48: =IFERROR( IF( NORMSDIST((NORMSINV($C48)-SQRT($D48)*F$40)/SQRT(1-$D48))<0.03%, 0.03%, NORMSDIST((NORMSINV($C48)-SQRT($D48)*F$40)/SQRT(1-$D48)) ), 0.03% ) -> 0.0040690229 | G48: =IFERROR( IF( NORMSDIST((NORMSINV($C48)-SQRT($D48)*G$40)/SQRT(1-$D48))<0.03%, 0.03%, NORMSDIST((NORMSINV($C48)-SQRT($D48)*G$40)/SQRT(1-$D48)) ), 0.03% ) -> 0.0026602318 | H48: =IFERROR( IF( NORMSDIST((NORMSINV($C48)-SQRT($D48)*H$40)/SQRT(1-$D48))<0.03%, 0.03%, NORMSDIST((NORMSINV($C48)-SQRT($D48)*H$40)/SQRT(1-$D48)) ), 0.03% ) -> 0.0016082894 | I48: =IFERROR( IF( NORMSDIST((NORMSINV($C48)-SQRT($D48)*I$40)/SQRT(1-$D48))<0.03%, 0.03%, NORMSDIST((NORMSINV($C48)-SQRT($D48)*I$40)/SQRT(1-$D48)) ), 0.03% ) -> 0.00089825047 | J48: =IFERROR( IF( NORMSDIST((NORMSINV($C48)-SQRT($D48)*J$40)/SQRT(1-$D48))<0.03%, 0.03%, NORMSDIST((NORMSINV($C48)-SQRT($D48)*J$40)/SQRT(1-$D48)) ), 0.03% ) -> 0.00045119812
B49: =B33 -> BBB | C49: =C18 -> 0.0221 | D49: =(0.12*(1-EXP(-50*C49))/(1-EXP(-50)))+0.24*(1-(1-EXP(-50*C49))/(1-EXP(-50))) -> 0.15974531 | E49: =IFERROR( IF( NORMSDIST((NORMSINV($C49)-SQRT($D49)*E$40)/SQRT(1-$D49))<0.03%, 0.03%, NORMSDIST((NORMSINV($C49)-SQRT($D49)*E$40)/SQRT(1-$D49)) ), 0.03% ) -> 0.0059275591 | F49: =IFERROR( IF( NORMSDIST((NORMSINV($C49)-SQRT($D49)*F$40)/SQRT(1-$D49))<0.03%, 0.03%, NORMSDIST((NORMSINV($C49)-SQRT($D49)*F$40)/SQRT(1-$D49)) ), 0.03% ) -> 0.0040690229 | G49: =IFERROR( IF( NORMSDIST((NORMSINV($C49)-SQRT($D49)*G$40)/SQRT(1-$D49))<0.03%, 0.03%, NORMSDIST((NORMSINV($C49)-SQRT($D49)*G$40)/SQRT(1-$D49)) ), 0.03% ) -> 0.0026602318 | H49: =IFERROR( IF( NORMSDIST((NORMSINV($C49)-SQRT($D49)*H$40)/SQRT(1-$D49))<0.03%, 0.03%, NORMSDIST((NORMSINV($C49)-SQRT($D49)*H$40)/SQRT(1-$D49)) ), 0.03% ) -> 0.0016082894 | I49: =IFERROR( IF( NORMSDIST((NORMSINV($C49)-SQRT($D49)*I$40)/SQRT(1-$D49))<0.03%, 0.03%, NORMSDIST((NORMSINV($C49)-SQRT($D49)*I$40)/SQRT(1-$D49)) ), 0.03% ) -> 0.00089825047 | J49: =IFERROR( IF( NORMSDIST((NORMSINV($C49)-SQRT($D49)*J$40)/SQRT(1-$D49))<0.03%, 0.03%, NORMSDIST((NORMSINV($C49)-SQRT($D49)*J$40)/SQRT(1-$D49)) ), 0.03% ) -> 0.00045119812
B50: =B34 -> BBB- | C50: =C19 -> 0.0221 | D50: =(0.12*(1-EXP(-50*C50))/(1-EXP(-50)))+0.24*(1-(1-EXP(-50*C50))/(1-EXP(-50))) -> 0.15974531 | E50: =IFERROR( IF( NORMSDIST((NORMSINV($C50)-SQRT($D50)*E$40)/SQRT(1-$D50))<0.03%, 0.03%, NORMSDIST((NORMSINV($C50)-SQRT($D50)*E$40)/SQRT(1-$D50)) ), 0.03% ) -> 0.0059275591 | F50: =IFERROR( IF( NORMSDIST((NORMSINV($C50)-SQRT($D50)*F$40)/SQRT(1-$D50))<0.03%, 0.03%, NORMSDIST((NORMSINV($C50)-SQRT($D50)*F$40)/SQRT(1-$D50)) ), 0.03% ) -> 0.0040690229 | G50: =IFERROR( IF( NORMSDIST((NORMSINV($C50)-SQRT($D50)*G$40)/SQRT(1-$D50))<0.03%, 0.03%, NORMSDIST((NORMSINV($C50)-SQRT($D50)*G$40)/SQRT(1-$D50)) ), 0.03% ) -> 0.0026602318 | H50: =IFERROR( IF( NORMSDIST((NORMSINV($C50)-SQRT($D50)*H$40)/SQRT(1-$D50))<0.03%, 0.03%, NORMSDIST((NORMSINV($C50)-SQRT($D50)*H$40)/SQRT(1-$D50)) ), 0.03% ) -> 0.0016082894 | I50: =IFERROR( IF( NORMSDIST((NORMSINV($C50)-SQRT($D50)*I$40)/SQRT(1-$D50))<0.03%, 0.03%, NORMSDIST((NORMSINV($C50)-SQRT($D50)*I$40)/SQRT(1-$D50)) ), 0.03% ) -> 0.00089825047 | J50: =IFERROR( IF( NORMSDIST((NORMSINV($C50)-SQRT($D50)*J$40)/SQRT(1-$D50))<0.03%, 0.03%, NORMSDIST((NORMSINV($C50)-SQRT($D50)*J$40)/SQRT(1-$D50)) ), 0.03% ) -> 0.00045119812
B51: =B35 -> BB+ | C51: =C20 -> 0.0992 | D51: =(0.12*(1-EXP(-50*C51))/(1-EXP(-50)))+0.24*(1-(1-EXP(-50*C51))/(1-EXP(-50))) -> 0.12084155 | E51: =IFERROR( IF( NORMSDIST((NORMSINV($C51)-SQRT($D51)*E$40)/SQRT(1-$D51))<0.03%, 0.03%, NORMSDIST((NORMSINV($C51)-SQRT($D51)*E$40)/SQRT(1-$D51)) ), 0.03% ) -> 0.050000318 | F51: =IFERROR( IF( NORMSDIST((NORMSINV($C51)-SQRT($D51)*F$40)/SQRT(1-$D51))<0.03%, 0.03%, NORMSDIST((NORMSINV($C51)-SQRT($D51)*F$40)/SQRT(1-$D51)) ), 0.03% ) -> 0.039606634 | G51: =IFERROR( IF( NORMSDIST((NORMSINV($C51)-SQRT($D51)*G$40)/SQRT(1-$D51))<0.03%, 0.03%, NORMSDIST((NORMSINV($C51)-SQRT($D51)*G$40)/SQRT(1-$D51)) ), 0.03% ) -> 0.030404418 | H51: =IFERROR( IF( NORMSDIST((NORMSINV($C51)-SQRT($D51)*H$40)/SQRT(1-$D51))<0.03%, 0.03%, NORMSDIST((NORMSINV($C51)-SQRT($D51)*H$40)/SQRT(1-$D51)) ), 0.03% ) -> 0.022198741 | I51: =IFERROR( IF( NORMSDIST((NORMSINV($C51)-SQRT($D51)*I$40)/SQRT(1-$D51))<0.03%, 0.03%, NORMSDIST((NORMSINV($C51)-SQRT($D51)*I$40)/SQRT(1-$D51)) ), 0.03% ) -> 0.015396829 | J51: =IFERROR( IF( NORMSDIST((NORMSINV($C51)-SQRT($D51)*J$40)/SQRT(1-$D51))<0.03%, 0.03%, NORMSDIST((NORMSINV($C51)-SQRT($D51)*J$40)/SQRT(1-$D51)) ), 0.03% ) -> 0.0099684567
B52: =B36 -> Unrated | C52: =C21 -> 0.0992 | D52: =(0.12*(1-EXP(-50*C52))/(1-EXP(-50)))+0.24*(1-(1-EXP(-50*C52))/(1-EXP(-50))) -> 0.12084155 | E52: =IFERROR( IF( NORMSDIST((NORMSINV($C52)-SQRT($D52)*E$40)/SQRT(1-$D52))<0.03%, 0.03%, NORMSDIST((NORMSINV($C52)-SQRT($D52)*E$40)/SQRT(1-$D52)) ), 0.03% ) -> 0.050000318 | F52: =IFERROR( IF( NORMSDIST((NORMSINV($C52)-SQRT($D52)*F$40)/SQRT(1-$D52))<0.03%, 0.03%, NORMSDIST((NORMSINV($C52)-SQRT($D52)*F$40)/SQRT(1-$D52)) ), 0.03% ) -> 0.039606634 | G52: =IFERROR( IF( NORMSDIST((NORMSINV($C52)-SQRT($D52)*G$40)/SQRT(1-$D52))<0.03%, 0.03%, NORMSDIST((NORMSINV($C52)-SQRT($D52)*G$40)/SQRT(1-$D52)) ), 0.03% ) -> 0.030404418 | H52: =IFERROR( IF( NORMSDIST((NORMSINV($C52)-SQRT($D52)*H$40)/SQRT(1-$D52))<0.03%, 0.03%, NORMSDIST((NORMSINV($C52)-SQRT($D52)*H$40)/SQRT(1-$D52)) ), 0.03% ) -> 0.022198741 | I52: =IFERROR( IF( NORMSDIST((NORMSINV($C52)-SQRT($D52)*I$40)/SQRT(1-$D52))<0.03%, 0.03%, NORMSDIST((NORMSINV($C52)-SQRT($D52)*I$40)/SQRT(1-$D52)) ), 0.03% ) -> 0.015396829 | J52: =IFERROR( IF( NORMSDIST((NORMSINV($C52)-SQRT($D52)*J$40)/SQRT(1-$D52))<0.03%, 0.03%, NORMSDIST((NORMSINV($C52)-SQRT($D52)*J$40)/SQRT(1-$D52)) ), 0.03% ) -> 0.0099684567

Sheet Survival Analysis
B6: Survival Analysis
B8: Base | K8: Upturn | T8: Downturn
B9: Grades | C9: TTC | D9: 2026 | E9: =D9+1 -> 2027 | F9: =E9+1 -> 2028 | G9: =F9+1 -> 2029 | H9: =G9+1 -> 2030 | I9: =H9+1 -> 2031 | K9: Grades | L9: TTC | M9: 2026 | N9: =M9+1 -> 2027 | O9: =N9+1 -> 2028 | P9: =O9+1 -> 2029 | Q9: =P9+1 -> 2030 | R9: =Q9+1 -> 2031 | T9: Grades | U9: TTC | V9: 2026 | W9: =V9+1 -> 2027 | X9: =W9+1 -> 2028 | Y9: =X9+1 -> 2029 | Z9: =Y9+1 -> 2030 | AA9: =Z9+1 -> 2031
B10: =Vasicek!B10 -> AAA | C10: =Vasicek!C10 -> 0.0003 | D10: =Vasicek!E10 -> 0.0003 | E10: =Vasicek!F10 -> 0.0003 | F10: =Vasicek!G10 -> 0.0003 | G10: =Vasicek!H10 -> 0.0003 | H10: =Vasicek!I10 -> 0.0003 | I10: =Vasicek!J10 -> 0.0003 | K10: =B10 -> AAA | L10: =C10 -> 0.0003 | M10: =Vasicek!E25 -> 0.0003 | N10: =Vasicek!F25 -> 0.0003 | O10: =Vasicek!G25 -> 0.0003 | P10: =Vasicek!H25 -> 0.0003 | Q10: =Vasicek!I25 -> 0.0003 | R10: =Vasicek!J25 -> 0.0003 | T10: =K10 -> AAA | U10: =L10 -> 0.0003 | V10: =Vasicek!E41 -> 0.0003 | W10: =Vasicek!F41 -> 0.0003 | X10: =Vasicek!G41 -> 0.0003 | Y10: =Vasicek!H41 -> 0.0003 | Z10: =Vasicek!I41 -> 0.0003 | AA10: =Vasicek!J41 -> 0.0003
B11: =Vasicek!B11 -> AA+ | C11: =Vasicek!C11 -> 0.0029 | D11: =Vasicek!E11 -> 0.0003 | E11: =Vasicek!F11 -> 0.0003 | F11: =Vasicek!G11 -> 0.0003 | G11: =Vasicek!H11 -> 0.0003 | H11: =Vasicek!I11 -> 0.0003 | I11: =Vasicek!J11 -> 0.0003 | K11: =B11 -> AA+ | L11: =C11 -> 0.0029 | M11: =Vasicek!E26 -> 0.0003 | N11: =Vasicek!F26 -> 0.0003 | O11: =Vasicek!G26 -> 0.0003 | P11: =Vasicek!H26 -> 0.0003 | Q11: =Vasicek!I26 -> 0.0003 | R11: =Vasicek!J26 -> 0.0003 | T11: =K11 -> AA+ | U11: =L11 -> 0.0029 | V11: =Vasicek!E42 -> 0.0003 | W11: =Vasicek!F42 -> 0.0003 | X11: =Vasicek!G42 -> 0.0003 | Y11: =Vasicek!H42 -> 0.0003 | Z11: =Vasicek!I42 -> 0.0003 | AA11: =Vasicek!J42 -> 0.0003
B12: =Vasicek!B12 -> AA | C12: =Vasicek!C12 -> 0.0029 | D12: =Vasicek!E12 -> 0.0003 | E12: =Vasicek!F12 -> 0.0003 | F12: =Vasicek!G12 -> 0.0003 | G12: =Vasicek!H12 -> 0.0003 | H12: =Vasicek!I12 -> 0.0003 | I12: =Vasicek!J12 -> 0.0003 | K12: =B12 -> AA | L12: =C12 -> 0.0029 | M12: =Vasicek!E27 -> 0.0003 | N12: =Vasicek!F27 -> 0.0003 | O12: =Vasicek!G27 -> 0.0003 | P12: =Vasicek!H27 -> 0.0003 | Q12: =Vasicek!I27 -> 0.0003 | R12: =Vasicek!J27 -> 0.0003 | T12: =K12 -> AA | U12: =L12 -> 0.0029 | V12: =Vasicek!E43 -> 0.0003 | W12: =Vasicek!F43 -> 0.0003 | X12: =Vasicek!G43 -> 0.0003 | Y12: =Vasicek!H43 -> 0.0003 | Z12: =Vasicek!I43 -> 0.0003 | AA12: =Vasicek!J43 -> 0.0003
B13: =Vasicek!B13 -> AA- | C13: =Vasicek!C13 -> 0.0029 | D13: =Vasicek!E13 -> 0.0003 | E13: =Vasicek!F13 -> 0.0003 | F13: =Vasicek!G13 -> 0.0003 | G13: =Vasicek!H13 -> 0.0003 | H13: =Vasicek!I13 -> 0.0003 | I13: =Vasicek!J13 -> 0.0003 | K13: =B13 -> AA- | L13: =C13 -> 0.0029 | M13: =Vasicek!E28 -> 0.0003 | N13: =Vasicek!F28 -> 0.0003 | O13: =Vasicek!G28 -> 0.0003 | P13: =Vasicek!H28 -> 0.0003 | Q13: =Vasicek!I28 -> 0.0003 | R13: =Vasicek!J28 -> 0.0003 | T13: =K13 -> AA- | U13: =L13 -> 0.0029 | V13: =Vasicek!E44 -> 0.0003 | W13: =Vasicek!F44 -> 0.0003 | X13: =Vasicek!G44 -> 0.0003 | Y13: =Vasicek!H44 -> 0.0003 | Z13: =Vasicek!I44 -> 0.0003 | AA13: =Vasicek!J44 -> 0.0003
B14: =Vasicek!B14 -> A+ | C14: =Vasicek!C14 -> 0.0066 | D14: =Vasicek!E14 -> 0.00068917818 | E14: =Vasicek!F14 -> 0.00037879399 | F14: =Vasicek!G14 -> 0.0003 | G14: =Vasicek!H14 -> 0.0003 | H14: =Vasicek!I14 -> 0.0003 | I14: =Vasicek!J14 -> 0.0003 | K14: =B14 -> A+ | L14: =C14 -> 0.0066 | M14: =Vasicek!E29 -> 0.00059580224 | N14: =Vasicek!F29 -> 0.00030576408 | O14: =Vasicek!G29 -> 0.0003 | P14: =Vasicek!H29 -> 0.0003 | Q14: =Vasicek!I29 -> 0.0003 | R14: =Vasicek!J29 -> 0.0003 | T14: =K14 -> A+ | U14: =L14 -> 0.0066 | V14: =Vasicek!E45 -> 0.00079589045 | W14: =Vasicek!F45 -> 0.00046775427 | X14: =Vasicek!G45 -> 0.0003 | Y14: =Vasicek!H45 -> 0.0003 | Z14: =Vasicek!I45 -> 0.0003 | AA14: =Vasicek!J45 -> 0.0003
B15: =Vasicek!B15 -> A | C15: =Vasicek!C15 -> 0.0066 | D15: =Vasicek!E15 -> 0.00068917818 | E15: =Vasicek!F15 -> 0.00037879399 | F15: =Vasicek!G15 -> 0.0003 | G15: =Vasicek!H15 -> 0.0003 | H15: =Vasicek!I15 -> 0.0003 | I15: =Vasicek!J15 -> 0.0003 | K15: =B15 -> A | L15: =C15 -> 0.0066 | M15: =Vasicek!E30 -> 0.00059580224 | N15: =Vasicek!F30 -> 0.00030576408 | O15: =Vasicek!G30 -> 0.0003 | P15: =Vasicek!H30 -> 0.0003 | Q15: =Vasicek!I30 -> 0.0003 | R15: =Vasicek!J30 -> 0.0003 | T15: =K15 -> A | U15: =L15 -> 0.0066 | V15: =Vasicek!E46 -> 0.00079589045 | W15: =Vasicek!F46 -> 0.00046775427 | X15: =Vasicek!G46 -> 0.0003 | Y15: =Vasicek!H46 -> 0.0003 | Z15: =Vasicek!I46 -> 0.0003 | AA15: =Vasicek!J46 -> 0.0003
B16: =Vasicek!B16 -> A- | C16: =Vasicek!C16 -> 0.0066 | D16: =Vasicek!E16 -> 0.00068917818 | E16: =Vasicek!F16 -> 0.00037879399 | F16: =Vasicek!G16 -> 0.0003 | G16: =Vasicek!H16 -> 0.0003 | H16: =Vasicek!I16 -> 0.0003 | I16: =Vasicek!J16 -> 0.0003 | K16: =B16 -> A- | L16: =C16 -> 0.0066 | M16: =Vasicek!E31 -> 0.00059580224 | N16: =Vasicek!F31 -> 0.00030576408 | O16: =Vasicek!G31 -> 0.0003 | P16: =Vasicek!H31 -> 0.0003 | Q16: =Vasicek!I31 -> 0.0003 | R16: =Vasicek!J31 -> 0.0003 | T16: =K16 -> A- | U16: =L16 -> 0.0066 | V16: =Vasicek!E47 -> 0.00079589045 | W16: =Vasicek!F47 -> 0.00046775427 | X16: =Vasicek!G47 -> 0.0003 | Y16: =Vasicek!H47 -> 0.0003 | Z16: =Vasicek!I47 -> 0.0003 | AA16: =Vasicek!J47 -> 0.0003
B17: =Vasicek!B17 -> BBB+ | C17: =Vasicek!C17 -> 0.0221 | D17: =Vasicek!E17 -> 0.005353392 | E17: =Vasicek!F17 -> 0.003504513 | F17: =Vasicek!G17 -> 0.0021673403 | G17: =Vasicek!H17 -> 0.0012239835 | H17: =Vasicek!I17 -> 0.00062999172 | I17: =Vasicek!J17 -> 0.0003 | K17: =B17 -> BBB+ | L17: =C17 -> 0.0221 | M17: =Vasicek!E32 -> 0.0048292177 | N17: =Vasicek!F32 -> 0.0030113581 | O17: =Vasicek!G32 -> 0.0017587271 | P17: =Vasicek!H32 -> 0.0009254922 | Q17: =Vasicek!I32 -> 0.00043748296 | R17: =Vasicek!J32 -> 0.0003 | T17: =K17 -> BBB+ | U17: =L17 -> 0.0221 | V17: =Vasicek!E48 -> 0.0059275591 | W17: =Vasicek!F48 -> 0.0040690229 | X17: =Vasicek!G48 -> 0.0026602318 | Y17: =Vasicek!H48 -> 0.0016082894 | Z17: =Vasicek!I48 -> 0.00089825047 | AA17: =Vasicek!J48 -> 0.00045119812
B18: =Vasicek!B18 -> BBB | C18: =Vasicek!C18 -> 0.0221 | D18: =Vasicek!E18 -> 0.005353392 | E18: =Vasicek!F18 -> 0.003504513 | F18: =Vasicek!G18 -> 0.0021673403 | G18: =Vasicek!H18 -> 0.0012239835 | H18: =Vasicek!I18 -> 0.00062999172 | I18: =Vasicek!J18 -> 0.0003 | K18: =B18 -> BBB | L18: =C18 -> 0.0221 | M18: =Vasicek!E33 -> 0.0048292177 | N18: =Vasicek!F33 -> 0.0030113581 | O18: =Vasicek!G33 -> 0.0017587271 | P18: =Vasicek!H33 -> 0.0009254922 | Q18: =Vasicek!I33 -> 0.00043748296 | R18: =Vasicek!J33 -> 0.0003 | T18: =K18 -> BBB | U18: =L18 -> 0.0221 | V18: =Vasicek!E49 -> 0.0059275591 | W18: =Vasicek!F49 -> 0.0040690229 | X18: =Vasicek!G49 -> 0.0026602318 | Y18: =Vasicek!H49 -> 0.0016082894 | Z18: =Vasicek!I49 -> 0.00089825047 | AA18: =Vasicek!J49 -> 0.00045119812
B19: =Vasicek!B19 -> BBB- | C19: =Vasicek!C19 -> 0.0221 | D19: =Vasicek!E19 -> 0.005353392 | E19: =Vasicek!F19 -> 0.003504513 | F19: =Vasicek!G19 -> 0.0021673403 | G19: =Vasicek!H19 -> 0.0012239835 | H19: =Vasicek!I19 -> 0.00062999172 | I19: =Vasicek!J19 -> 0.0003 | K19: =B19 -> BBB- | L19: =C19 -> 0.0221 | M19: =Vasicek!E34 -> 0.0048292177 | N19: =Vasicek!F34 -> 0.0030113581 | O19: =Vasicek!G34 -> 0.0017587271 | P19: =Vasicek!H34 -> 0.0009254922 | Q19: =Vasicek!I34 -> 0.00043748296 | R19: =Vasicek!J34 -> 0.0003 | T19: =K19 -> BBB- | U19: =L19 -> 0.0221 | V19: =Vasicek!E50 -> 0.0059275591 | W19: =Vasicek!F50 -> 0.0040690229 | X19: =Vasicek!G50 -> 0.0026602318 | Y19: =Vasicek!H50 -> 0.0016082894 | Z19: =Vasicek!I50 -> 0.00089825047 | AA19: =Vasicek!J50 -> 0.00045119812
B20: =Vasicek!B20 -> BB+ | C20: =Vasicek!C20 -> 0.0992 | D20: =Vasicek!E20 -> 0.046947093 | E20: =Vasicek!F20 -> 0.036097097 | F20: =Vasicek!G20 -> 0.026754164 | G20: =Vasicek!H20 -> 0.018704154 | H20: =Vasicek!I20 -> 0.012310709 | I20: =Vasicek!J20 -> 0.0074718577 | K20: =B20 -> BB+ | L20: =C20 -> 0.0992 | M20: =Vasicek!E35 -> 0.044045227 | N20: =Vasicek!F35 -> 0.032846413 | O20: =Vasicek!G35 -> 0.023477361 | P20: =Vasicek!H35 -> 0.015689193 | Q20: =Vasicek!I35 -> 0.0097755354 | R20: =Vasicek!J35 -> 0.0055434565 | T20: =K20 -> BB+ | U20: =L20 -> 0.0992 | V20: =Vasicek!E51 -> 0.050000318 | W20: =Vasicek!F51 -> 0.039606634 | X20: =Vasicek!G51 -> 0.030404418 | Y20: =Vasicek!H51 -> 0.022198741 | Z20: =Vasicek!I51 -> 0.015396829 | AA20: =Vasicek!J51 -> 0.0099684567
B21: =Vasicek!B21 -> Unrated | C21: =Vasicek!C21 -> 0.0992 | D21: =Vasicek!E21 -> 0.046947093 | E21: =Vasicek!F21 -> 0.036097097 | F21: =Vasicek!G21 -> 0.026754164 | G21: =Vasicek!H21 -> 0.018704154 | H21: =Vasicek!I21 -> 0.012310709 | I21: =Vasicek!J21 -> 0.0074718577 | K21: =B21 -> Unrated | L21: =C21 -> 0.0992 | M21: =Vasicek!E36 -> 0.044045227 | N21: =Vasicek!F36 -> 0.032846413 | O21: =Vasicek!G36 -> 0.023477361 | P21: =Vasicek!H36 -> 0.015689193 | Q21: =Vasicek!I36 -> 0.0097755354 | R21: =Vasicek!J36 -> 0.0055434565 | T21: =K21 -> Unrated | U21: =L21 -> 0.0992 | V21: =Vasicek!E52 -> 0.050000318 | W21: =Vasicek!F52 -> 0.039606634 | X21: =Vasicek!G52 -> 0.030404418 | Y21: =Vasicek!H52 -> 0.022198741 | Z21: =Vasicek!I52 -> 0.015396829 | AA21: =Vasicek!J52 -> 0.0099684567
B24: Base | C24: (1-p) | K24: Upturn | L24: (1-p) | T24: Downturn | U24: (1-p)
B25: Grades | C25: TTC | D25: 2026 | E25: =D25+1 -> 2027 | F25: =E25+1 -> 2028 | G25: =F25+1 -> 2029 | H25: =G25+1 -> 2030 | I25: =H25+1 -> 2031 | K25: Grades | L25: TTC | M25: 2026 | N25: =M25+1 -> 2027 | O25: =N25+1 -> 2028 | P25: =O25+1 -> 2029 | Q25: =P25+1 -> 2030 | R25: =Q25+1 -> 2031 | T25: Grades | U25: TTC | V25: 2026 | W25: =V25+1 -> 2027 | X25: =W25+1 -> 2028 | Y25: =X25+1 -> 2029 | Z25: =Y25+1 -> 2030 | AA25: =Z25+1 -> 2031
B26: =B10 -> AAA | C26: =C10 -> 0.0003 | D26: =1-D10 -> 0.9997 | E26: =1-E10 -> 0.9997 | F26: =1-F10 -> 0.9997 | G26: =1-G10 -> 0.9997 | H26: =1-H10 -> 0.9997 | I26: =1-I10 -> 0.9997 | K26: =B26 -> AAA | L26: =C26 -> 0.0003 | M26: =1-M10 -> 0.9997 | N26: =1-N10 -> 0.9997 | O26: =1-O10 -> 0.9997 | P26: =1-P10 -> 0.9997 | Q26: =1-Q10 -> 0.9997 | R26: =1-R10 -> 0.9997 | T26: =T10 -> AAA | U26: =C26 -> 0.0003 | V26: =1-V10 -> 0.9997 | W26: =1-W10 -> 0.9997 | X26: =1-X10 -> 0.9997 | Y26: =1-Y10 -> 0.9997 | Z26: =1-Z10 -> 0.9997 | AA26: =1-AA10 -> 0.9997
B27: =B11 -> AA+ | C27: =C11 -> 0.0029 | D27: =1-D11 -> 0.9997 | E27: =1-E11 -> 0.9997 | F27: =1-F11 -> 0.9997 | G27: =1-G11 -> 0.9997 | H27: =1-H11 -> 0.9997 | I27: =1-I11 -> 0.9997 | K27: =B27 -> AA+ | L27: =C27 -> 0.0029 | M27: =1-M11 -> 0.9997 | N27: =1-N11 -> 0.9997 | O27: =1-O11 -> 0.9997 | P27: =1-P11 -> 0.9997 | Q27: =1-Q11 -> 0.9997 | R27: =1-R11 -> 0.9997 | T27: =T11 -> AA+ | U27: =C27 -> 0.0029 | V27: =1-V11 -> 0.9997 | W27: =1-W11 -> 0.9997 | X27: =1-X11 -> 0.9997 | Y27: =1-Y11 -> 0.9997 | Z27: =1-Z11 -> 0.9997 | AA27: =1-AA11 -> 0.9997
B28: =B12 -> AA | C28: =C12 -> 0.0029 | D28: =1-D12 -> 0.9997 | E28: =1-E12 -> 0.9997 | F28: =1-F12 -> 0.9997 | G28: =1-G12 -> 0.9997 | H28: =1-H12 -> 0.9997 | I28: =1-I12 -> 0.9997 | K28: =B28 -> AA | L28: =C28 -> 0.0029 | M28: =1-M12 -> 0.9997 | N28: =1-N12 -> 0.9997 | O28: =1-O12 -> 0.9997 | P28: =1-P12 -> 0.9997 | Q28: =1-Q12 -> 0.9997 | R28: =1-R12 -> 0.9997 | T28: =T12 -> AA | U28: =C28 -> 0.0029 | V28: =1-V12 -> 0.9997 | W28: =1-W12 -> 0.9997 | X28: =1-X12 -> 0.9997 | Y28: =1-Y12 -> 0.9997 | Z28: =1-Z12 -> 0.9997 | AA28: =1-AA12 -> 0.9997
B29: =B13 -> AA- | C29: =C13 -> 0.0029 | D29: =1-D13 -> 0.9997 | E29: =1-E13 -> 0.9997 | F29: =1-F13 -> 0.9997 | G29: =1-G13 -> 0.9997 | H29: =1-H13 -> 0.9997 | I29: =1-I13 -> 0.9997 | K29: =B29 -> AA- | L29: =C29 -> 0.0029 | M29: =1-M13 -> 0.9997 | N29: =1-N13 -> 0.9997 | O29: =1-O13 -> 0.9997 | P29: =1-P13 -> 0.9997 | Q29: =1-Q13 -> 0.9997 | R29: =1-R13 -> 0.9997 | T29: =T13 -> AA- | U29: =C29 -> 0.0029 | V29: =1-V13 -> 0.9997 | W29: =1-W13 -> 0.9997 | X29: =1-X13 -> 0.9997 | Y29: =1-Y13 -> 0.9997 | Z29: =1-Z13 -> 0.9997 | AA29: =1-AA13 -> 0.9997
B30: =B14 -> A+ | C30: =C14 -> 0.0066 | D30: =1-D14 -> 0.99931082 | E30: =1-E14 -> 0.99962121 | F30: =1-F14 -> 0.9997 | G30: =1-G14 -> 0.9997 | H30: =1-H14 -> 0.9997 | I30: =1-I14 -> 0.9997 | K30: =B30 -> A+ | L30: =C30 -> 0.0066 | M30: =1-M14 -> 0.9994042 | N30: =1-N14 -> 0.99969424 | O30: =1-O14 -> 0.9997 | P30: =1-P14 -> 0.9997 | Q30: =1-Q14 -> 0.9997 | R30: =1-R14 -> 0.9997 | T30: =T14 -> A+ | U30: =C30 -> 0.0066 | V30: =1-V14 -> 0.99920411 | W30: =1-W14 -> 0.99953225 | X30: =1-X14 -> 0.9997 | Y30: =1-Y14 -> 0.9997 | Z30: =1-Z14 -> 0.9997 | AA30: =1-AA14 -> 0.9997
B31: =B15 -> A | C31: =C15 -> 0.0066 | D31: =1-D15 -> 0.99931082 | E31: =1-E15 -> 0.99962121 | F31: =1-F15 -> 0.9997 | G31: =1-G15 -> 0.9997 | H31: =1-H15 -> 0.9997 | I31: =1-I15 -> 0.9997 | K31: =B31 -> A | L31: =C31 -> 0.0066 | M31: =1-M15 -> 0.9994042 | N31: =1-N15 -> 0.99969424 | O31: =1-O15 -> 0.9997 | P31: =1-P15 -> 0.9997 | Q31: =1-Q15 -> 0.9997 | R31: =1-R15 -> 0.9997 | T31: =T15 -> A | U31: =C31 -> 0.0066 | V31: =1-V15 -> 0.99920411 | W31: =1-W15 -> 0.99953225 | X31: =1-X15 -> 0.9997 | Y31: =1-Y15 -> 0.9997 | Z31: =1-Z15 -> 0.9997 | AA31: =1-AA15 -> 0.9997
B32: =B16 -> A- | C32: =C16 -> 0.0066 | D32: =1-D16 -> 0.99931082 | E32: =1-E16 -> 0.99962121 | F32: =1-F16 -> 0.9997 | G32: =1-G16 -> 0.9997 | H32: =1-H16 -> 0.9997 | I32: =1-I16 -> 0.9997 | K32: =B32 -> A- | L32: =C32 -> 0.0066 | M32: =1-M16 -> 0.9994042 | N32: =1-N16 -> 0.99969424 | O32: =1-O16 -> 0.9997 | P32: =1-P16 -> 0.9997 | Q32: =1-Q16 -> 0.9997 | R32: =1-R16 -> 0.9997 | T32: =T16 -> A- | U32: =C32 -> 0.0066 | V32: =1-V16 -> 0.99920411 | W32: =1-W16 -> 0.99953225 | X32: =1-X16 -> 0.9997 | Y32: =1-Y16 -> 0.9997 | Z32: =1-Z16 -> 0.9997 | AA32: =1-AA16 -> 0.9997
B33: =B17 -> BBB+ | C33: =C17 -> 0.0221 | D33: =1-D17 -> 0.99464661 | E33: =1-E17 -> 0.99649549 | F33: =1-F17 -> 0.99783266 | G33: =1-G17 -> 0.99877602 | H33: =1-H17 -> 0.99937001 | I33: =1-I17 -> 0.9997 | K33: =B33 -> BBB+ | L33: =C33 -> 0.0221 | M33: =1-M17 -> 0.99517078 | N33: =1-N17 -> 0.99698864 | O33: =1-O17 -> 0.99824127 | P33: =1-P17 -> 0.99907451 | Q33: =1-Q17 -> 0.99956252 | R33: =1-R17 -> 0.9997 | T33: =T17 -> BBB+ | U33: =C33 -> 0.0221 | V33: =1-V17 -> 0.99407244 | W33: =1-W17 -> 0.99593098 | X33: =1-X17 -> 0.99733977 | Y33: =1-Y17 -> 0.99839171 | Z33: =1-Z17 -> 0.99910175 | AA33: =1-AA17 -> 0.9995488
B34: =B18 -> BBB | C34: =C18 -> 0.0221 | D34: =1-D18 -> 0.99464661 | E34: =1-E18 -> 0.99649549 | F34: =1-F18 -> 0.99783266 | G34: =1-G18 -> 0.99877602 | H34: =1-H18 -> 0.99937001 | I34: =1-I18 -> 0.9997 | K34: =B34 -> BBB | L34: =C34 -> 0.0221 | M34: =1-M18 -> 0.99517078 | N34: =1-N18 -> 0.99698864 | O34: =1-O18 -> 0.99824127 | P34: =1-P18 -> 0.99907451 | Q34: =1-Q18 -> 0.99956252 | R34: =1-R18 -> 0.9997 | T34: =T18 -> BBB | U34: =C34 -> 0.0221 | V34: =1-V18 -> 0.99407244 | W34: =1-W18 -> 0.99593098 | X34: =1-X18 -> 0.99733977 | Y34: =1-Y18 -> 0.99839171 | Z34: =1-Z18 -> 0.99910175 | AA34: =1-AA18 -> 0.9995488
B35: =B19 -> BBB- | C35: =C19 -> 0.0221 | D35: =1-D19 -> 0.99464661 | E35: =1-E19 -> 0.99649549 | F35: =1-F19 -> 0.99783266 | G35: =1-G19 -> 0.99877602 | H35: =1-H19 -> 0.99937001 | I35: =1-I19 -> 0.9997 | K35: =B35 -> BBB- | L35: =C35 -> 0.0221 | M35: =1-M19 -> 0.99517078 | N35: =1-N19 -> 0.99698864 | O35: =1-O19 -> 0.99824127 | P35: =1-P19 -> 0.99907451 | Q35: =1-Q19 -> 0.99956252 | R35: =1-R19 -> 0.9997 | T35: =T19 -> BBB- | U35: =C35 -> 0.0221 | V35: =1-V19 -> 0.99407244 | W35: =1-W19 -> 0.99593098 | X35: =1-X19 -> 0.99733977 | Y35: =1-Y19 -> 0.99839171 | Z35: =1-Z19 -> 0.99910175 | AA35: =1-AA19 -> 0.9995488
B36: =B20 -> BB+ | C36: =C20 -> 0.0992 | D36: =1-D20 -> 0.95305291 | E36: =1-E20 -> 0.9639029 | F36: =1-F20 -> 0.97324584 | G36: =1-G20 -> 0.98129585 | H36: =1-H20 -> 0.98768929 | I36: =1-I20 -> 0.99252814 | K36: =B36 -> BB+ | L36: =C36 -> 0.0992 | M36: =1-M20 -> 0.95595477 | N36: =1-N20 -> 0.96715359 | O36: =1-O20 -> 0.97652264 | P36: =1-P20 -> 0.98431081 | Q36: =1-Q20 -> 0.99022446 | R36: =1-R20 -> 0.99445654 | T36: =T20 -> BB+ | U36: =C36 -> 0.0992 | V36: =1-V20 -> 0.94999968 | W36: =1-W20 -> 0.96039337 | X36: =1-X20 -> 0.96959558 | Y36: =1-Y20 -> 0.97780126 | Z36: =1-Z20 -> 0.98460317 | AA36: =1-AA20 -> 0.99003154
B37: =B21 -> Unrated | C37: =C21 -> 0.0992 | D37: =1-D21 -> 0.95305291 | E37: =1-E21 -> 0.9639029 | F37: =1-F21 -> 0.97324584 | G37: =1-G21 -> 0.98129585 | H37: =1-H21 -> 0.98768929 | I37: =1-I21 -> 0.99252814 | K37: =B37 -> Unrated | L37: =C37 -> 0.0992 | M37: =1-M21 -> 0.95595477 | N37: =1-N21 -> 0.96715359 | O37: =1-O21 -> 0.97652264 | P37: =1-P21 -> 0.98431081 | Q37: =1-Q21 -> 0.99022446 | R37: =1-R21 -> 0.99445654 | T37: =T21 -> Unrated | U37: =C37 -> 0.0992 | V37: =1-V21 -> 0.94999968 | W37: =1-W21 -> 0.96039337 | X37: =1-X21 -> 0.96959558 | Y37: =1-Y21 -> 0.97780126 | Z37: =1-Z21 -> 0.98460317 | AA37: =1-AA21 -> 0.99003154
B40: Base | C40: (1-p)*(1-p)…. | K40: Upturn | L40: (1-p)*(1-p)…. | T40: Downturn | U40: (1-p)*(1-p)….
B41: Grades | C41: TTC | D41: 2026 | E41: =D41+1 -> 2027 | F41: =E41+1 -> 2028 | G41: =F41+1 -> 2029 | H41: =G41+1 -> 2030 | I41: =H41+1 -> 2031 | K41: Grades | L41: TTC | M41: 2026 | N41: =M41+1 -> 2027 | O41: =N41+1 -> 2028 | P41: =O41+1 -> 2029 | Q41: =P41+1 -> 2030 | R41: =Q41+1 -> 2031 | T41: Grades | U41: TTC | V41: 2026 | W41: =V41+1 -> 2027 | X41: =W41+1 -> 2028 | Y41: =X41+1 -> 2029 | Z41: =Y41+1 -> 2030 | AA41: =Z41+1 -> 2031
B42: =B26 -> AAA | C42: =C10 -> 0.0003 | D42: =PRODUCT(D26) -> 0.9997 | E42: =PRODUCT(E26) -> 0.9997 | F42: =PRODUCT(F26) -> 0.9997 | G42: =PRODUCT(G26) -> 0.9997 | H42: =PRODUCT(H26) -> 0.9997 | I42: =PRODUCT(I26) -> 0.9997 | K42: =B42 -> AAA | L42: =C42 -> 0.0003 | M42: =PRODUCT(M26) -> 0.9997 | N42: =PRODUCT(N26) -> 0.9997 | O42: =PRODUCT(O26) -> 0.9997 | P42: =PRODUCT(P26) -> 0.9997 | Q42: =PRODUCT(Q26) -> 0.9997 | R42: =PRODUCT(R26) -> 0.9997 | T42: =K42 -> AAA | U42: =L42 -> 0.0003 | V42: =PRODUCT(V26) -> 0.9997 | W42: =PRODUCT(W26) -> 0.9997 | X42: =PRODUCT(X26) -> 0.9997 | Y42: =PRODUCT(Y26) -> 0.9997 | Z42: =PRODUCT(Z26) -> 0.9997 | AA42: =PRODUCT(AA26) -> 0.9997
B43: =B27 -> AA+ | C43: =C11 -> 0.0029 | D43: =PRODUCT(D27) -> 0.9997 | E43: =PRODUCT(E27) -> 0.9997 | F43: =PRODUCT(F27) -> 0.9997 | G43: =PRODUCT(G27) -> 0.9997 | H43: =PRODUCT(H27) -> 0.9997 | I43: =PRODUCT(I27) -> 0.9997 | K43: =B43 -> AA+ | L43: =C43 -> 0.0029 | M43: =PRODUCT(M27) -> 0.9997 | N43: =PRODUCT(N27) -> 0.9997 | O43: =PRODUCT(O27) -> 0.9997 | P43: =PRODUCT(P27) -> 0.9997 | Q43: =PRODUCT(Q27) -> 0.9997 | R43: =PRODUCT(R27) -> 0.9997 | T43: =K43 -> AA+ | U43: =L43 -> 0.0029 | V43: =PRODUCT(V27) -> 0.9997 | W43: =PRODUCT(W27) -> 0.9997 | X43: =PRODUCT(X27) -> 0.9997 | Y43: =PRODUCT(Y27) -> 0.9997 | Z43: =PRODUCT(Z27) -> 0.9997 | AA43: =PRODUCT(AA27) -> 0.9997
B44: =B28 -> AA | C44: =C12 -> 0.0029 | D44: =PRODUCT(D28) -> 0.9997 | E44: =PRODUCT(E28) -> 0.9997 | F44: =PRODUCT(F28) -> 0.9997 | G44: =PRODUCT(G28) -> 0.9997 | H44: =PRODUCT(H28) -> 0.9997 | I44: =PRODUCT(I28) -> 0.9997 | K44: =B44 -> AA | L44: =C44 -> 0.0029 | M44: =PRODUCT(M28) -> 0.9997 | N44: =PRODUCT(N28) -> 0.9997 | O44: =PRODUCT(O28) -> 0.9997 | P44: =PRODUCT(P28) -> 0.9997 | Q44: =PRODUCT(Q28) -> 0.9997 | R44: =PRODUCT(R28) -> 0.9997 | T44: =K44 -> AA | U44: =L44 -> 0.0029 | V44: =PRODUCT(V28) -> 0.9997 | W44: =PRODUCT(W28) -> 0.9997 | X44: =PRODUCT(X28) -> 0.9997 | Y44: =PRODUCT(Y28) -> 0.9997 | Z44: =PRODUCT(Z28) -> 0.9997 | AA44: =PRODUCT(AA28) -> 0.9997
B45: =B29 -> AA- | C45: =C13 -> 0.0029 | D45: =PRODUCT(D29) -> 0.9997 | E45: =PRODUCT(E29) -> 0.9997 | F45: =PRODUCT(F29) -> 0.9997 | G45: =PRODUCT(G29) -> 0.9997 | H45: =PRODUCT(H29) -> 0.9997 | I45: =PRODUCT(I29) -> 0.9997 | K45: =B45 -> AA- | L45: =C45 -> 0.0029 | M45: =PRODUCT(M29) -> 0.9997 | N45: =PRODUCT(N29) -> 0.9997 | O45: =PRODUCT(O29) -> 0.9997 | P45: =PRODUCT(P29) -> 0.9997 | Q45: =PRODUCT(Q29) -> 0.9997 | R45: =PRODUCT(R29) -> 0.9997 | T45: =K45 -> AA- | U45: =L45 -> 0.0029 | V45: =PRODUCT(V29) -> 0.9997 | W45: =PRODUCT(W29) -> 0.9997 | X45: =PRODUCT(X29) -> 0.9997 | Y45: =PRODUCT(Y29) -> 0.9997 | Z45: =PRODUCT(Z29) -> 0.9997 | AA45: =PRODUCT(AA29) -> 0.9997
B46: =B30 -> A+ | C46: =C14 -> 0.0066 | D46: =PRODUCT(D30) -> 0.99931082 | E46: =PRODUCT(E30) -> 0.99962121 | F46: =PRODUCT(F30) -> 0.9997 | G46: =PRODUCT(G30) -> 0.9997 | H46: =PRODUCT(H30) -> 0.9997 | I46: =PRODUCT(I30) -> 0.9997 | K46: =B46 -> A+ | L46: =C46 -> 0.0066 | M46: =PRODUCT(M30) -> 0.9994042 | N46: =PRODUCT(N30) -> 0.99969424 | O46: =PRODUCT(O30) -> 0.9997 | P46: =PRODUCT(P30) -> 0.9997 | Q46: =PRODUCT(Q30) -> 0.9997 | R46: =PRODUCT(R30) -> 0.9997 | T46: =K46 -> A+ | U46: =L46 -> 0.0066 | V46: =PRODUCT(V30) -> 0.99920411 | W46: =PRODUCT(W30) -> 0.99953225 | X46: =PRODUCT(X30) -> 0.9997 | Y46: =PRODUCT(Y30) -> 0.9997 | Z46: =PRODUCT(Z30) -> 0.9997 | AA46: =PRODUCT(AA30) -> 0.9997
B47: =B31 -> A | C47: =C15 -> 0.0066 | D47: =PRODUCT(D31) -> 0.99931082 | E47: =PRODUCT(E31) -> 0.99962121 | F47: =PRODUCT(F31) -> 0.9997 | G47: =PRODUCT(G31) -> 0.9997 | H47: =PRODUCT(H31) -> 0.9997 | I47: =PRODUCT(I31) -> 0.9997 | K47: =B47 -> A | L47: =C47 -> 0.0066 | M47: =PRODUCT(M31) -> 0.9994042 | N47: =PRODUCT(N31) -> 0.99969424 | O47: =PRODUCT(O31) -> 0.9997 | P47: =PRODUCT(P31) -> 0.9997 | Q47: =PRODUCT(Q31) -> 0.9997 | R47: =PRODUCT(R31) -> 0.9997 | T47: =K47 -> A | U47: =L47 -> 0.0066 | V47: =PRODUCT(V31) -> 0.99920411 | W47: =PRODUCT(W31) -> 0.99953225 | X47: =PRODUCT(X31) -> 0.9997 | Y47: =PRODUCT(Y31) -> 0.9997 | Z47: =PRODUCT(Z31) -> 0.9997 | AA47: =PRODUCT(AA31) -> 0.9997
B48: =B32 -> A- | C48: =C16 -> 0.0066 | D48: =PRODUCT(D32) -> 0.99931082 | E48: =PRODUCT(E32) -> 0.99962121 | F48: =PRODUCT(F32) -> 0.9997 | G48: =PRODUCT(G32) -> 0.9997 | H48: =PRODUCT(H32) -> 0.9997 | I48: =PRODUCT(I32) -> 0.9997 | K48: =B48 -> A- | L48: =C48 -> 0.0066 | M48: =PRODUCT(M32) -> 0.9994042 | N48: =PRODUCT(N32) -> 0.99969424 | O48: =PRODUCT(O32) -> 0.9997 | P48: =PRODUCT(P32) -> 0.9997 | Q48: =PRODUCT(Q32) -> 0.9997 | R48: =PRODUCT(R32) -> 0.9997 | T48: =K48 -> A- | U48: =L48 -> 0.0066 | V48: =PRODUCT(V32) -> 0.99920411 | W48: =PRODUCT(W32) -> 0.99953225 | X48: =PRODUCT(X32) -> 0.9997 | Y48: =PRODUCT(Y32) -> 0.9997 | Z48: =PRODUCT(Z32) -> 0.9997 | AA48: =PRODUCT(AA32) -> 0.9997
B49: =B33 -> BBB+ | C49: =C17 -> 0.0221 | D49: =PRODUCT(D33) -> 0.99464661 | E49: =PRODUCT(E33) -> 0.99649549 | F49: =PRODUCT(F33) -> 0.99783266 | G49: =PRODUCT(G33) -> 0.99877602 | H49: =PRODUCT(H33) -> 0.99937001 | I49: =PRODUCT(I33) -> 0.9997 | K49: =B49 -> BBB+ | L49: =C49 -> 0.0221 | M49: =PRODUCT(M33) -> 0.99517078 | N49: =PRODUCT(N33) -> 0.99698864 | O49: =PRODUCT(O33) -> 0.99824127 | P49: =PRODUCT(P33) -> 0.99907451 | Q49: =PRODUCT(Q33) -> 0.99956252 | R49: =PRODUCT(R33) -> 0.9997 | T49: =K49 -> BBB+ | U49: =L49 -> 0.0221 | V49: =PRODUCT(V33) -> 0.99407244 | W49: =PRODUCT(W33) -> 0.99593098 | X49: =PRODUCT(X33) -> 0.99733977 | Y49: =PRODUCT(Y33) -> 0.99839171 | Z49: =PRODUCT(Z33) -> 0.99910175 | AA49: =PRODUCT(AA33) -> 0.9995488
B50: =B34 -> BBB | C50: =C18 -> 0.0221 | D50: =PRODUCT(D34) -> 0.99464661 | E50: =PRODUCT(E34) -> 0.99649549 | F50: =PRODUCT(F34) -> 0.99783266 | G50: =PRODUCT(G34) -> 0.99877602 | H50: =PRODUCT(H34) -> 0.99937001 | I50: =PRODUCT(I34) -> 0.9997 | K50: =B50 -> BBB | L50: =C50 -> 0.0221 | M50: =PRODUCT(M34) -> 0.99517078 | N50: =PRODUCT(N34) -> 0.99698864 | O50: =PRODUCT(O34) -> 0.99824127 | P50: =PRODUCT(P34) -> 0.99907451 | Q50: =PRODUCT(Q34) -> 0.99956252 | R50: =PRODUCT(R34) -> 0.9997 | T50: =K50 -> BBB | U50: =L50 -> 0.0221 | V50: =PRODUCT(V34) -> 0.99407244 | W50: =PRODUCT(W34) -> 0.99593098 | X50: =PRODUCT(X34) -> 0.99733977 | Y50: =PRODUCT(Y34) -> 0.99839171 | Z50: =PRODUCT(Z34) -> 0.99910175 | AA50: =PRODUCT(AA34) -> 0.9995488
B51: =B35 -> BBB- | C51: =C19 -> 0.0221 | D51: =PRODUCT(D35) -> 0.99464661 | E51: =PRODUCT(E35) -> 0.99649549 | F51: =PRODUCT(F35) -> 0.99783266 | G51: =PRODUCT(G35) -> 0.99877602 | H51: =PRODUCT(H35) -> 0.99937001 | I51: =PRODUCT(I35) -> 0.9997 | K51: =B51 -> BBB- | L51: =C51 -> 0.0221 | M51: =PRODUCT(M35) -> 0.99517078 | N51: =PRODUCT(N35) -> 0.99698864 | O51: =PRODUCT(O35) -> 0.99824127 | P51: =PRODUCT(P35) -> 0.99907451 | Q51: =PRODUCT(Q35) -> 0.99956252 | R51: =PRODUCT(R35) -> 0.9997 | T51: =K51 -> BBB- | U51: =L51 -> 0.0221 | V51: =PRODUCT(V35) -> 0.99407244 | W51: =PRODUCT(W35) -> 0.99593098 | X51: =PRODUCT(X35) -> 0.99733977 | Y51: =PRODUCT(Y35) -> 0.99839171 | Z51: =PRODUCT(Z35) -> 0.99910175 | AA51: =PRODUCT(AA35) -> 0.9995488
B52: =B36 -> BB+ | C52: =C20 -> 0.0992 | D52: =PRODUCT(D36) -> 0.95305291 | E52: =PRODUCT(E36) -> 0.9639029 | F52: =PRODUCT(F36) -> 0.97324584 | G52: =PRODUCT(G36) -> 0.98129585 | H52: =PRODUCT(H36) -> 0.98768929 | I52: =PRODUCT(I36) -> 0.99252814 | K52: =B52 -> BB+ | L52: =C52 -> 0.0992 | M52: =PRODUCT(M36) -> 0.95595477 | N52: =PRODUCT(N36) -> 0.96715359 | O52: =PRODUCT(O36) -> 0.97652264 | P52: =PRODUCT(P36) -> 0.98431081 | Q52: =PRODUCT(Q36) -> 0.99022446 | R52: =PRODUCT(R36) -> 0.99445654 | T52: =K52 -> BB+ | U52: =L52 -> 0.0992 | V52: =PRODUCT(V36) -> 0.94999968 | W52: =PRODUCT(W36) -> 0.96039337 | X52: =PRODUCT(X36) -> 0.96959558 | Y52: =PRODUCT(Y36) -> 0.97780126 | Z52: =PRODUCT(Z36) -> 0.98460317 | AA52: =PRODUCT(AA36) -> 0.99003154
B53: =B37 -> Unrated | C53: =C21 -> 0.0992 | D53: =PRODUCT(D37) -> 0.95305291 | E53: =PRODUCT(E37) -> 0.9639029 | F53: =PRODUCT(F37) -> 0.97324584 | G53: =PRODUCT(G37) -> 0.98129585 | H53: =PRODUCT(H37) -> 0.98768929 | I53: =PRODUCT(I37) -> 0.99252814 | K53: =B53 -> Unrated | L53: =C53 -> 0.0992 | M53: =PRODUCT(M37) -> 0.95595477 | N53: =PRODUCT(N37) -> 0.96715359 | O53: =PRODUCT(O37) -> 0.97652264 | P53: =PRODUCT(P37) -> 0.98431081 | Q53: =PRODUCT(Q37) -> 0.99022446 | R53: =PRODUCT(R37) -> 0.99445654 | T53: =K53 -> Unrated | U53: =L53 -> 0.0992 | V53: =PRODUCT(V37) -> 0.94999968 | W53: =PRODUCT(W37) -> 0.96039337 | X53: =PRODUCT(X37) -> 0.96959558 | Y53: =PRODUCT(Y37) -> 0.97780126 | Z53: =PRODUCT(Z37) -> 0.98460317 | AA53: =PRODUCT(AA37) -> 0.99003154

Sheet PIT PD
B6: Forecast Marginal Probability of Default
B8: Base | K8: Upturn | T8: Downturn
B9: Grades | C9: TTC | D9: 2026 | E9: =D9+1 -> 2027 | F9: =E9+1 -> 2028 | G9: =F9+1 -> 2029 | H9: =G9+1 -> 2030 | I9: =H9+1 -> 2031 | K9: Grades | L9: TTC | M9: 2026 | N9: =M9+1 -> 2027 | O9: =N9+1 -> 2028 | P9: =O9+1 -> 2029 | Q9: =P9+1 -> 2030 | R9: =Q9+1 -> 2031 | T9: Grades | U9: TTC | V9: 2026 | W9: =V9+1 -> 2027 | X9: =W9+1 -> 2028 | Y9: =X9+1 -> 2029 | Z9: =Y9+1 -> 2030 | AA9: =Z9+1 -> 2031
B10: ='Survival Analysis'!B10 -> AAA | C10: ='Survival Analysis'!C10 -> 0.0003 | D10: ='Survival Analysis'!D10 -> 0.0003 | E10: ='Survival Analysis'!E10*'Survival Analysis'!D42 -> 0.00029991 | F10: ='Survival Analysis'!F10*'Survival Analysis'!E42 -> 0.00029991 | G10: ='Survival Analysis'!G10*'Survival Analysis'!F42 -> 0.00029991 | H10: ='Survival Analysis'!H10*'Survival Analysis'!G42 -> 0.00029991 | I10: ='Survival Analysis'!I10*'Survival Analysis'!H42 -> 0.00029991 | K10: =B10 -> AAA | L10: =C10 -> 0.0003 | M10: ='Survival Analysis'!M10 -> 0.0003 | N10: ='Survival Analysis'!N10*'Survival Analysis'!M42 -> 0.00029991 | O10: ='Survival Analysis'!O10*'Survival Analysis'!N42 -> 0.00029991 | P10: ='Survival Analysis'!P10*'Survival Analysis'!O42 -> 0.00029991 | Q10: ='Survival Analysis'!Q10*'Survival Analysis'!P42 -> 0.00029991 | R10: ='Survival Analysis'!R10*'Survival Analysis'!Q42 -> 0.00029991 | T10: =K10 -> AAA | U10: =L10 -> 0.0003 | V10: ='Survival Analysis'!V10 -> 0.0003 | W10: ='Survival Analysis'!W10*'Survival Analysis'!V42 -> 0.00029991 | X10: ='Survival Analysis'!X10*'Survival Analysis'!W42 -> 0.00029991 | Y10: ='Survival Analysis'!Y10*'Survival Analysis'!X42 -> 0.00029991 | Z10: ='Survival Analysis'!Z10*'Survival Analysis'!Y42 -> 0.00029991 | AA10: ='Survival Analysis'!AA10*'Survival Analysis'!Z42 -> 0.00029991
B11: ='Survival Analysis'!B11 -> AA+ | C11: ='Survival Analysis'!C11 -> 0.0029 | D11: ='Survival Analysis'!D11 -> 0.0003 | E11: ='Survival Analysis'!E11*'Survival Analysis'!D43 -> 0.00029991 | F11: ='Survival Analysis'!F11*'Survival Analysis'!E43 -> 0.00029991 | G11: ='Survival Analysis'!G11*'Survival Analysis'!F43 -> 0.00029991 | H11: ='Survival Analysis'!H11*'Survival Analysis'!G43 -> 0.00029991 | I11: ='Survival Analysis'!I11*'Survival Analysis'!H43 -> 0.00029991 | K11: =B11 -> AA+ | L11: =C11 -> 0.0029 | M11: ='Survival Analysis'!M11 -> 0.0003 | N11: ='Survival Analysis'!N11*'Survival Analysis'!M43 -> 0.00029991 | O11: ='Survival Analysis'!O11*'Survival Analysis'!N43 -> 0.00029991 | P11: ='Survival Analysis'!P11*'Survival Analysis'!O43 -> 0.00029991 | Q11: ='Survival Analysis'!Q11*'Survival Analysis'!P43 -> 0.00029991 | R11: ='Survival Analysis'!R11*'Survival Analysis'!Q43 -> 0.00029991 | T11: =K11 -> AA+ | U11: =L11 -> 0.0029 | V11: ='Survival Analysis'!V11 -> 0.0003 | W11: ='Survival Analysis'!W11*'Survival Analysis'!V43 -> 0.00029991 | X11: ='Survival Analysis'!X11*'Survival Analysis'!W43 -> 0.00029991 | Y11: ='Survival Analysis'!Y11*'Survival Analysis'!X43 -> 0.00029991 | Z11: ='Survival Analysis'!Z11*'Survival Analysis'!Y43 -> 0.00029991 | AA11: ='Survival Analysis'!AA11*'Survival Analysis'!Z43 -> 0.00029991
B12: ='Survival Analysis'!B12 -> AA | C12: ='Survival Analysis'!C12 -> 0.0029 | D12: ='Survival Analysis'!D12 -> 0.0003 | E12: ='Survival Analysis'!E12*'Survival Analysis'!D44 -> 0.00029991 | F12: ='Survival Analysis'!F12*'Survival Analysis'!E44 -> 0.00029991 | G12: ='Survival Analysis'!G12*'Survival Analysis'!F44 -> 0.00029991 | H12: ='Survival Analysis'!H12*'Survival Analysis'!G44 -> 0.00029991 | I12: ='Survival Analysis'!I12*'Survival Analysis'!H44 -> 0.00029991 | K12: =B12 -> AA | L12: =C12 -> 0.0029 | M12: ='Survival Analysis'!M12 -> 0.0003 | N12: ='Survival Analysis'!N12*'Survival Analysis'!M44 -> 0.00029991 | O12: ='Survival Analysis'!O12*'Survival Analysis'!N44 -> 0.00029991 | P12: ='Survival Analysis'!P12*'Survival Analysis'!O44 -> 0.00029991 | Q12: ='Survival Analysis'!Q12*'Survival Analysis'!P44 -> 0.00029991 | R12: ='Survival Analysis'!R12*'Survival Analysis'!Q44 -> 0.00029991 | T12: =K12 -> AA | U12: =L12 -> 0.0029 | V12: ='Survival Analysis'!V12 -> 0.0003 | W12: ='Survival Analysis'!W12*'Survival Analysis'!V44 -> 0.00029991 | X12: ='Survival Analysis'!X12*'Survival Analysis'!W44 -> 0.00029991 | Y12: ='Survival Analysis'!Y12*'Survival Analysis'!X44 -> 0.00029991 | Z12: ='Survival Analysis'!Z12*'Survival Analysis'!Y44 -> 0.00029991 | AA12: ='Survival Analysis'!AA12*'Survival Analysis'!Z44 -> 0.00029991
B13: ='Survival Analysis'!B13 -> AA- | C13: ='Survival Analysis'!C13 -> 0.0029 | D13: ='Survival Analysis'!D13 -> 0.0003 | E13: ='Survival Analysis'!E13*'Survival Analysis'!D45 -> 0.00029991 | F13: ='Survival Analysis'!F13*'Survival Analysis'!E45 -> 0.00029991 | G13: ='Survival Analysis'!G13*'Survival Analysis'!F45 -> 0.00029991 | H13: ='Survival Analysis'!H13*'Survival Analysis'!G45 -> 0.00029991 | I13: ='Survival Analysis'!I13*'Survival Analysis'!H45 -> 0.00029991 | K13: =B13 -> AA- | L13: =C13 -> 0.0029 | M13: ='Survival Analysis'!M13 -> 0.0003 | N13: ='Survival Analysis'!N13*'Survival Analysis'!M45 -> 0.00029991 | O13: ='Survival Analysis'!O13*'Survival Analysis'!N45 -> 0.00029991 | P13: ='Survival Analysis'!P13*'Survival Analysis'!O45 -> 0.00029991 | Q13: ='Survival Analysis'!Q13*'Survival Analysis'!P45 -> 0.00029991 | R13: ='Survival Analysis'!R13*'Survival Analysis'!Q45 -> 0.00029991 | T13: =K13 -> AA- | U13: =L13 -> 0.0029 | V13: ='Survival Analysis'!V13 -> 0.0003 | W13: ='Survival Analysis'!W13*'Survival Analysis'!V45 -> 0.00029991 | X13: ='Survival Analysis'!X13*'Survival Analysis'!W45 -> 0.00029991 | Y13: ='Survival Analysis'!Y13*'Survival Analysis'!X45 -> 0.00029991 | Z13: ='Survival Analysis'!Z13*'Survival Analysis'!Y45 -> 0.00029991 | AA13: ='Survival Analysis'!AA13*'Survival Analysis'!Z45 -> 0.00029991
B14: ='Survival Analysis'!B14 -> A+ | C14: ='Survival Analysis'!C14 -> 0.0066 | D14: ='Survival Analysis'!D14 -> 0.00068917818 | E14: ='Survival Analysis'!E14*'Survival Analysis'!D46 -> 0.00037853293 | F14: ='Survival Analysis'!F14*'Survival Analysis'!E46 -> 0.00029988636 | G14: ='Survival Analysis'!G14*'Survival Analysis'!F46 -> 0.00029991 | H14: ='Survival Analysis'!H14*'Survival Analysis'!G46 -> 0.00029991 | I14: ='Survival Analysis'!I14*'Survival Analysis'!H46 -> 0.00029991 | K14: =B14 -> A+ | L14: =C14 -> 0.0066 | M14: ='Survival Analysis'!M14 -> 0.00059580224 | N14: ='Survival Analysis'!N14*'Survival Analysis'!M46 -> 0.00030558191 | O14: ='Survival Analysis'!O14*'Survival Analysis'!N46 -> 0.00029990827 | P14: ='Survival Analysis'!P14*'Survival Analysis'!O46 -> 0.00029991 | Q14: ='Survival Analysis'!Q14*'Survival Analysis'!P46 -> 0.00029991 | R14: ='Survival Analysis'!R14*'Survival Analysis'!Q46 -> 0.00029991 | T14: =K14 -> A+ | U14: =L14 -> 0.0066 | V14: ='Survival Analysis'!V14 -> 0.00079589045 | W14: ='Survival Analysis'!W14*'Survival Analysis'!V46 -> 0.00046738199 | X14: ='Survival Analysis'!X14*'Survival Analysis'!W46 -> 0.00029985967 | Y14: ='Survival Analysis'!Y14*'Survival Analysis'!X46 -> 0.00029991 | Z14: ='Survival Analysis'!Z14*'Survival Analysis'!Y46 -> 0.00029991 | AA14: ='Survival Analysis'!AA14*'Survival Analysis'!Z46 -> 0.00029991
B15: ='Survival Analysis'!B15 -> A | C15: ='Survival Analysis'!C15 -> 0.0066 | D15: ='Survival Analysis'!D15 -> 0.00068917818 | E15: ='Survival Analysis'!E15*'Survival Analysis'!D47 -> 0.00037853293 | F15: ='Survival Analysis'!F15*'Survival Analysis'!E47 -> 0.00029988636 | G15: ='Survival Analysis'!G15*'Survival Analysis'!F47 -> 0.00029991 | H15: ='Survival Analysis'!H15*'Survival Analysis'!G47 -> 0.00029991 | I15: ='Survival Analysis'!I15*'Survival Analysis'!H47 -> 0.00029991 | K15: =B15 -> A | L15: =C15 -> 0.0066 | M15: ='Survival Analysis'!M15 -> 0.00059580224 | N15: ='Survival Analysis'!N15*'Survival Analysis'!M47 -> 0.00030558191 | O15: ='Survival Analysis'!O15*'Survival Analysis'!N47 -> 0.00029990827 | P15: ='Survival Analysis'!P15*'Survival Analysis'!O47 -> 0.00029991 | Q15: ='Survival Analysis'!Q15*'Survival Analysis'!P47 -> 0.00029991 | R15: ='Survival Analysis'!R15*'Survival Analysis'!Q47 -> 0.00029991 | T15: =K15 -> A | U15: =L15 -> 0.0066 | V15: ='Survival Analysis'!V15 -> 0.00079589045 | W15: ='Survival Analysis'!W15*'Survival Analysis'!V47 -> 0.00046738199 | X15: ='Survival Analysis'!X15*'Survival Analysis'!W47 -> 0.00029985967 | Y15: ='Survival Analysis'!Y15*'Survival Analysis'!X47 -> 0.00029991 | Z15: ='Survival Analysis'!Z15*'Survival Analysis'!Y47 -> 0.00029991 | AA15: ='Survival Analysis'!AA15*'Survival Analysis'!Z47 -> 0.00029991
B16: ='Survival Analysis'!B16 -> A- | C16: ='Survival Analysis'!C16 -> 0.0066 | D16: ='Survival Analysis'!D16 -> 0.00068917818 | E16: ='Survival Analysis'!E16*'Survival Analysis'!D48 -> 0.00037853293 | F16: ='Survival Analysis'!F16*'Survival Analysis'!E48 -> 0.00029988636 | G16: ='Survival Analysis'!G16*'Survival Analysis'!F48 -> 0.00029991 | H16: ='Survival Analysis'!H16*'Survival Analysis'!G48 -> 0.00029991 | I16: ='Survival Analysis'!I16*'Survival Analysis'!H48 -> 0.00029991 | K16: =B16 -> A- | L16: =C16 -> 0.0066 | M16: ='Survival Analysis'!M16 -> 0.00059580224 | N16: ='Survival Analysis'!N16*'Survival Analysis'!M48 -> 0.00030558191 | O16: ='Survival Analysis'!O16*'Survival Analysis'!N48 -> 0.00029990827 | P16: ='Survival Analysis'!P16*'Survival Analysis'!O48 -> 0.00029991 | Q16: ='Survival Analysis'!Q16*'Survival Analysis'!P48 -> 0.00029991 | R16: ='Survival Analysis'!R16*'Survival Analysis'!Q48 -> 0.00029991 | T16: =K16 -> A- | U16: =L16 -> 0.0066 | V16: ='Survival Analysis'!V16 -> 0.00079589045 | W16: ='Survival Analysis'!W16*'Survival Analysis'!V48 -> 0.00046738199 | X16: ='Survival Analysis'!X16*'Survival Analysis'!W48 -> 0.00029985967 | Y16: ='Survival Analysis'!Y16*'Survival Analysis'!X48 -> 0.00029991 | Z16: ='Survival Analysis'!Z16*'Survival Analysis'!Y48 -> 0.00029991 | AA16: ='Survival Analysis'!AA16*'Survival Analysis'!Z48 -> 0.00029991
B17: ='Survival Analysis'!B17 -> BBB+ | C17: ='Survival Analysis'!C17 -> 0.0221 | D17: ='Survival Analysis'!D17 -> 0.005353392 | E17: ='Survival Analysis'!E17*'Survival Analysis'!D49 -> 0.003485752 | F17: ='Survival Analysis'!F17*'Survival Analysis'!E49 -> 0.0021597449 | G17: ='Survival Analysis'!G17*'Survival Analysis'!F49 -> 0.0012213307 | H17: ='Survival Analysis'!H17*'Survival Analysis'!G49 -> 0.00062922062 | I17: ='Survival Analysis'!I17*'Survival Analysis'!H49 -> 0.000299811 | K17: =B17 -> BBB+ | L17: =C17 -> 0.0221 | M17: ='Survival Analysis'!M17 -> 0.0048292177 | N17: ='Survival Analysis'!N17*'Survival Analysis'!M49 -> 0.0029968156 | O17: ='Survival Analysis'!O17*'Survival Analysis'!N49 -> 0.001753431 | P17: ='Survival Analysis'!P17*'Survival Analysis'!O49 -> 0.00092386451 | Q17: ='Survival Analysis'!Q17*'Survival Analysis'!P49 -> 0.00043707808 | R17: ='Survival Analysis'!R17*'Survival Analysis'!Q49 -> 0.00029986876 | T17: =K17 -> BBB+ | U17: =L17 -> 0.0221 | V17: ='Survival Analysis'!V17 -> 0.0059275591 | W17: ='Survival Analysis'!W17*'Survival Analysis'!V49 -> 0.0040449036 | X17: ='Survival Analysis'!X17*'Survival Analysis'!W49 -> 0.0026494073 | Y17: ='Survival Analysis'!Y17*'Survival Analysis'!X49 -> 0.001604011 | Z17: ='Survival Analysis'!Z17*'Survival Analysis'!Y49 -> 0.00089680582 | AA17: ='Survival Analysis'!AA17*'Survival Analysis'!Z49 -> 0.00045079283
B18: ='Survival Analysis'!B18 -> BBB | C18: ='Survival Analysis'!C18 -> 0.0221 | D18: ='Survival Analysis'!D18 -> 0.005353392 | E18: ='Survival Analysis'!E18*'Survival Analysis'!D50 -> 0.003485752 | F18: ='Survival Analysis'!F18*'Survival Analysis'!E50 -> 0.0021597449 | G18: ='Survival Analysis'!G18*'Survival Analysis'!F50 -> 0.0012213307 | H18: ='Survival Analysis'!H18*'Survival Analysis'!G50 -> 0.00062922062 | I18: ='Survival Analysis'!I18*'Survival Analysis'!H50 -> 0.000299811 | K18: =B18 -> BBB | L18: =C18 -> 0.0221 | M18: ='Survival Analysis'!M18 -> 0.0048292177 | N18: ='Survival Analysis'!N18*'Survival Analysis'!M50 -> 0.0029968156 | O18: ='Survival Analysis'!O18*'Survival Analysis'!N50 -> 0.001753431 | P18: ='Survival Analysis'!P18*'Survival Analysis'!O50 -> 0.00092386451 | Q18: ='Survival Analysis'!Q18*'Survival Analysis'!P50 -> 0.00043707808 | R18: ='Survival Analysis'!R18*'Survival Analysis'!Q50 -> 0.00029986876 | T18: =K18 -> BBB | U18: =L18 -> 0.0221 | V18: ='Survival Analysis'!V18 -> 0.0059275591 | W18: ='Survival Analysis'!W18*'Survival Analysis'!V50 -> 0.0040449036 | X18: ='Survival Analysis'!X18*'Survival Analysis'!W50 -> 0.0026494073 | Y18: ='Survival Analysis'!Y18*'Survival Analysis'!X50 -> 0.001604011 | Z18: ='Survival Analysis'!Z18*'Survival Analysis'!Y50 -> 0.00089680582 | AA18: ='Survival Analysis'!AA18*'Survival Analysis'!Z50 -> 0.00045079283
B19: ='Survival Analysis'!B19 -> BBB- | C19: ='Survival Analysis'!C19 -> 0.0221 | D19: ='Survival Analysis'!D19 -> 0.005353392 | E19: ='Survival Analysis'!E19*'Survival Analysis'!D51 -> 0.003485752 | F19: ='Survival Analysis'!F19*'Survival Analysis'!E51 -> 0.0021597449 | G19: ='Survival Analysis'!G19*'Survival Analysis'!F51 -> 0.0012213307 | H19: ='Survival Analysis'!H19*'Survival Analysis'!G51 -> 0.00062922062 | I19: ='Survival Analysis'!I19*'Survival Analysis'!H51 -> 0.000299811 | K19: =B19 -> BBB- | L19: =C19 -> 0.0221 | M19: ='Survival Analysis'!M19 -> 0.0048292177 | N19: ='Survival Analysis'!N19*'Survival Analysis'!M51 -> 0.0029968156 | O19: ='Survival Analysis'!O19*'Survival Analysis'!N51 -> 0.001753431 | P19: ='Survival Analysis'!P19*'Survival Analysis'!O51 -> 0.00092386451 | Q19: ='Survival Analysis'!Q19*'Survival Analysis'!P51 -> 0.00043707808 | R19: ='Survival Analysis'!R19*'Survival Analysis'!Q51 -> 0.00029986876 | T19: =K19 -> BBB- | U19: =L19 -> 0.0221 | V19: ='Survival Analysis'!V19 -> 0.0059275591 | W19: ='Survival Analysis'!W19*'Survival Analysis'!V51 -> 0.0040449036 | X19: ='Survival Analysis'!X19*'Survival Analysis'!W51 -> 0.0026494073 | Y19: ='Survival Analysis'!Y19*'Survival Analysis'!X51 -> 0.001604011 | Z19: ='Survival Analysis'!Z19*'Survival Analysis'!Y51 -> 0.00089680582 | AA19: ='Survival Analysis'!AA19*'Survival Analysis'!Z51 -> 0.00045079283
B20: ='Survival Analysis'!B20 -> BB+ | C20: ='Survival Analysis'!C20 -> 0.0992 | D20: ='Survival Analysis'!D20 -> 0.046947093 | E20: ='Survival Analysis'!E20*'Survival Analysis'!D52 -> 0.034402443 | F20: ='Survival Analysis'!F20*'Survival Analysis'!E52 -> 0.025788417 | G20: ='Survival Analysis'!G20*'Survival Analysis'!F52 -> 0.01820374 | H20: ='Survival Analysis'!H20*'Survival Analysis'!G52 -> 0.012080448 | I20: ='Survival Analysis'!I20*'Survival Analysis'!H52 -> 0.0073798739 | K20: =B20 -> BB+ | L20: =C20 -> 0.0992 | M20: ='Survival Analysis'!M20 -> 0.044045227 | N20: ='Survival Analysis'!N20*'Survival Analysis'!M52 -> 0.031399685 | O20: ='Survival Analysis'!O20*'Survival Analysis'!N52 -> 0.022706213 | P20: ='Survival Analysis'!P20*'Survival Analysis'!O52 -> 0.015320852 | Q20: ='Survival Analysis'!Q20*'Survival Analysis'!P52 -> 0.0096221651 | R20: ='Survival Analysis'!R20*'Survival Analysis'!Q52 -> 0.0054892663 | T20: =K20 -> BB+ | U20: =L20 -> 0.0992 | V20: ='Survival Analysis'!V20 -> 0.050000318 | W20: ='Survival Analysis'!W20*'Survival Analysis'!V52 -> 0.03762629 | X20: ='Survival Analysis'!X20*'Survival Analysis'!W52 -> 0.029200201 | Y20: ='Survival Analysis'!Y20*'Survival Analysis'!X52 -> 0.021523801 | Z20: ='Survival Analysis'!Z20*'Survival Analysis'!Y52 -> 0.015055039 | AA20: ='Survival Analysis'!AA20*'Survival Analysis'!Z52 -> 0.0098149741
B21: ='Survival Analysis'!B21 -> Unrated | C21: ='Survival Analysis'!C21 -> 0.0992 | D21: ='Survival Analysis'!D21 -> 0.046947093 | E21: ='Survival Analysis'!E21*'Survival Analysis'!D53 -> 0.034402443 | F21: ='Survival Analysis'!F21*'Survival Analysis'!E53 -> 0.025788417 | G21: ='Survival Analysis'!G21*'Survival Analysis'!F53 -> 0.01820374 | H21: ='Survival Analysis'!H21*'Survival Analysis'!G53 -> 0.012080448 | I21: ='Survival Analysis'!I21*'Survival Analysis'!H53 -> 0.0073798739 | K21: =B21 -> Unrated | L21: =C21 -> 0.0992 | M21: ='Survival Analysis'!M21 -> 0.044045227 | N21: ='Survival Analysis'!N21*'Survival Analysis'!M53 -> 0.031399685 | O21: ='Survival Analysis'!O21*'Survival Analysis'!N53 -> 0.022706213 | P21: ='Survival Analysis'!P21*'Survival Analysis'!O53 -> 0.015320852 | Q21: ='Survival Analysis'!Q21*'Survival Analysis'!P53 -> 0.0096221651 | R21: ='Survival Analysis'!R21*'Survival Analysis'!Q53 -> 0.0054892663 | T21: =K21 -> Unrated | U21: =L21 -> 0.0992 | V21: ='Survival Analysis'!V21 -> 0.050000318 | W21: ='Survival Analysis'!W21*'Survival Analysis'!V53 -> 0.03762629 | X21: ='Survival Analysis'!X21*'Survival Analysis'!W53 -> 0.029200201 | Y21: ='Survival Analysis'!Y21*'Survival Analysis'!X53 -> 0.021523801 | Z21: ='Survival Analysis'!Z21*'Survival Analysis'!Y53 -> 0.015055039 | AA21: ='Survival Analysis'!AA21*'Survival Analysis'!Z53 -> 0.0098149741
B23: Scenario Weights
B25: Base | C25: Upturn | D25: Downturn
B26: =Admin!B10 -> 0.5 | C26: =Admin!C10 -> 0.05 | D26: =Admin!D10 -> 0.45
B28: Point-In-Time Probability of Default
B30: PIT PD
B31: Grades | C31: TTC | D31: 2026 | E31: =D31+1 -> 2027 | F31: =E31+1 -> 2028 | G31: =F31+1 -> 2029 | H31: =G31+1 -> 2030 | I31: =H31+1 -> 2031 | J31: Life time PD
B32: =B10 -> AAA | C32: =C10 -> 0.0003 | D32: =$B$26*D10+$C$26*M10+$D$26*V10 -> 0.0003 | E32: =$B$26*E10+$C$26*N10+$D$26*W10 -> 0.00029991 | F32: =$B$26*F10+$C$26*O10+$D$26*X10 -> 0.00029991 | G32: =$B$26*G10+$C$26*P10+$D$26*Y10 -> 0.00029991 | H32: =$B$26*H10+$C$26*Q10+$D$26*Z10 -> 0.00029991 | I32: =$B$26*I10+$C$26*R10+$D$26*AA10 -> 0.00029991 | J32: =SUM(E32:I32) -> 0.00149955
B33: =B11 -> AA+ | C33: =C11 -> 0.0029 | D33: =$B$26*D11+$C$26*M11+$D$26*V11 -> 0.0003 | E33: =$B$26*E11+$C$26*N11+$D$26*W11 -> 0.00029991 | F33: =$B$26*F11+$C$26*O11+$D$26*X11 -> 0.00029991 | G33: =$B$26*G11+$C$26*P11+$D$26*Y11 -> 0.00029991 | H33: =$B$26*H11+$C$26*Q11+$D$26*Z11 -> 0.00029991 | I33: =$B$26*I11+$C$26*R11+$D$26*AA11 -> 0.00029991 | J33: =SUM(E33:I33) -> 0.00149955
B34: =B12 -> AA | C34: =C12 -> 0.0029 | D34: =$B$26*D12+$C$26*M12+$D$26*V12 -> 0.0003 | E34: =$B$26*E12+$C$26*N12+$D$26*W12 -> 0.00029991 | F34: =$B$26*F12+$C$26*O12+$D$26*X12 -> 0.00029991 | G34: =$B$26*G12+$C$26*P12+$D$26*Y12 -> 0.00029991 | H34: =$B$26*H12+$C$26*Q12+$D$26*Z12 -> 0.00029991 | I34: =$B$26*I12+$C$26*R12+$D$26*AA12 -> 0.00029991 | J34: =SUM(E34:I34) -> 0.00149955
B35: =B13 -> AA- | C35: =C13 -> 0.0029 | D35: =$B$26*D13+$C$26*M13+$D$26*V13 -> 0.0003 | E35: =$B$26*E13+$C$26*N13+$D$26*W13 -> 0.00029991 | F35: =$B$26*F13+$C$26*O13+$D$26*X13 -> 0.00029991 | G35: =$B$26*G13+$C$26*P13+$D$26*Y13 -> 0.00029991 | H35: =$B$26*H13+$C$26*Q13+$D$26*Z13 -> 0.00029991 | I35: =$B$26*I13+$C$26*R13+$D$26*AA13 -> 0.00029991 | J35: =SUM(E35:I35) -> 0.00149955
B36: =B14 -> A+ | C36: =C14 -> 0.0066 | D36: =$B$26*D14+$C$26*M14+$D$26*V14 -> 0.0007325299 | E36: =$B$26*E14+$C$26*N14+$D$26*W14 -> 0.00041486746 | F36: =$B$26*F14+$C$26*O14+$D$26*X14 -> 0.00029987545 | G36: =$B$26*G14+$C$26*P14+$D$26*Y14 -> 0.00029991 | H36: =$B$26*H14+$C$26*Q14+$D$26*Z14 -> 0.00029991 | I36: =$B$26*I14+$C$26*R14+$D$26*AA14 -> 0.00029991 | J36: =SUM(E36:I36) -> 0.0016144729
B37: =B15 -> A | C37: =C15 -> 0.0066 | D37: =$B$26*D15+$C$26*M15+$D$26*V15 -> 0.0007325299 | E37: =$B$26*E15+$C$26*N15+$D$26*W15 -> 0.00041486746 | F37: =$B$26*F15+$C$26*O15+$D$26*X15 -> 0.00029987545 | G37: =$B$26*G15+$C$26*P15+$D$26*Y15 -> 0.00029991 | H37: =$B$26*H15+$C$26*Q15+$D$26*Z15 -> 0.00029991 | I37: =$B$26*I15+$C$26*R15+$D$26*AA15 -> 0.00029991 | J37: =SUM(E37:I37) -> 0.0016144729
B38: =B16 -> A- | C38: =C16 -> 0.0066 | D38: =$B$26*D16+$C$26*M16+$D$26*V16 -> 0.0007325299 | E38: =$B$26*E16+$C$26*N16+$D$26*W16 -> 0.00041486746 | F38: =$B$26*F16+$C$26*O16+$D$26*X16 -> 0.00029987545 | G38: =$B$26*G16+$C$26*P16+$D$26*Y16 -> 0.00029991 | H38: =$B$26*H16+$C$26*Q16+$D$26*Z16 -> 0.00029991 | I38: =$B$26*I16+$C$26*R16+$D$26*AA16 -> 0.00029991 | J38: =SUM(E38:I38) -> 0.0016144729
B39: =B17 -> BBB+ | C39: =C17 -> 0.0221 | D39: =$B$26*D17+$C$26*M17+$D$26*V17 -> 0.0055855585 | E39: =$B$26*E17+$C$26*N17+$D$26*W17 -> 0.0037129234 | F39: =$B$26*F17+$C$26*O17+$D$26*X17 -> 0.0023597773 | G39: =$B$26*G17+$C$26*P17+$D$26*Y17 -> 0.0013786635 | H39: =$B$26*H17+$C$26*Q17+$D$26*Z17 -> 0.00074002683 | I39: =$B$26*I17+$C$26*R17+$D$26*AA17 -> 0.00036775571 | J39: =SUM(E39:I39) -> 0.0085591467
B40: =B18 -> BBB | C40: =C18 -> 0.0221 | D40: =$B$26*D18+$C$26*M18+$D$26*V18 -> 0.0055855585 | E40: =$B$26*E18+$C$26*N18+$D$26*W18 -> 0.0037129234 | F40: =$B$26*F18+$C$26*O18+$D$26*X18 -> 0.0023597773 | G40: =$B$26*G18+$C$26*P18+$D$26*Y18 -> 0.0013786635 | H40: =$B$26*H18+$C$26*Q18+$D$26*Z18 -> 0.00074002683 | I40: =$B$26*I18+$C$26*R18+$D$26*AA18 -> 0.00036775571 | J40: =SUM(E40:I40) -> 0.0085591467
B41: =B19 -> BBB- | C41: =C19 -> 0.0221 | D41: =$B$26*D19+$C$26*M19+$D$26*V19 -> 0.0055855585 | E41: =$B$26*E19+$C$26*N19+$D$26*W19 -> 0.0037129234 | F41: =$B$26*F19+$C$26*O19+$D$26*X19 -> 0.0023597773 | G41: =$B$26*G19+$C$26*P19+$D$26*Y19 -> 0.0013786635 | H41: =$B$26*H19+$C$26*Q19+$D$26*Z19 -> 0.00074002683 | I41: =$B$26*I19+$C$26*R19+$D$26*AA19 -> 0.00036775571 | J41: =SUM(E41:I41) -> 0.0085591467
B42: =B20 -> BB+ | C42: =C20 -> 0.0992 | D42: =$B$26*D20+$C$26*M20+$D$26*V20 -> 0.048175951 | E42: =$B$26*E20+$C$26*N20+$D$26*W20 -> 0.035703036 | F42: =$B$26*F20+$C$26*O20+$D$26*X20 -> 0.02716961 | G42: =$B$26*G20+$C$26*P20+$D$26*Y20 -> 0.019553623 | H42: =$B$26*H20+$C$26*Q20+$D$26*Z20 -> 0.013296099 | I42: =$B$26*I20+$C$26*R20+$D$26*AA20 -> 0.0083811386 | J42: =SUM(E42:I42) -> 0.10410351
B43: =B21 -> Unrated | C43: =C21 -> 0.0992 | D43: =$B$26*D21+$C$26*M21+$D$26*V21 -> 0.048175951 | E43: =$B$26*E21+$C$26*N21+$D$26*W21 -> 0.035703036 | F43: =$B$26*F21+$C$26*O21+$D$26*X21 -> 0.02716961 | G43: =$B$26*G21+$C$26*P21+$D$26*Y21 -> 0.019553623 | H43: =$B$26*H21+$C$26*Q21+$D$26*Z21 -> 0.013296099 | I43: =$B$26*I21+$C$26*R21+$D$26*AA21 -> 0.0083811386 | J43: =SUM(E43:I43) -> 0.10410351

Sheet ECL Calculation
B6: ECL Computation: | C6: EAD
B7: Grades | C7: Stage 1 | D7: Stage 2 | E7: Stage 3 | F7: PD | G7: Lifetime PD | H7: LGD | I7: ECL | K7: ECL Computation | L7: Amt in Crores
B8: ='PIT PD'!B32 -> AAA | C8: ='Input Data '!T9 -> 16859.79 | D8: ='Input Data '!U9 -> 0 | E8: ='Input Data '!V9 -> 0 | F8: ='PIT PD'!D32 -> 0.0003 | G8: =IF('Input Data '!N9="Y",'PIT PD'!J32,0) -> 0 | H8: 0.65 | I8: =(C8*F8+D8*G8+E8*1)*H8 -> 3.2876591 | K8: A. ECL as per the Model | L8: =I20 -> 110.07907
B9: ='PIT PD'!B33 -> AA+ | C9: ='Input Data '!T10 -> 1103.85 | D9: ='Input Data '!U10 -> 0 | E9: ='Input Data '!V10 -> 0 | F9: ='PIT PD'!D33 -> 0.0003 | G9: =IF('Input Data '!N10="Y",'PIT PD'!J33,0) -> 0 | H9: 0.65 | I9: =(C9*F9+D9*G9+E9*1)*H9 -> 0.21525075 | K9: B. ECL as per IRAC Minimum Provision | L9: =SUM('Input Data '!F9:F22)*0.4% -> 143.19572
B10: ='PIT PD'!B34 -> AA | C10: ='Input Data '!T11 -> 12103.75 | D10: ='Input Data '!U11 -> 0 | E10: ='Input Data '!V11 -> 0 | F10: ='PIT PD'!D34 -> 0.0003 | G10: =IF('Input Data '!N11="Y",'PIT PD'!J34,0) -> 0 | H10: 0.65 | I10: =(C10*F10+D10*G10+E10*1)*H10 -> 2.3602313 | K10: C. Final ECL (Max of A or B) | L10: =MAX(L8,L9) -> 143.19572
B11: ='PIT PD'!B35 -> AA- | C11: ='Input Data '!T12 -> 0 | D11: ='Input Data '!U12 -> 0 | E11: ='Input Data '!V12 -> 0 | F11: ='PIT PD'!D35 -> 0.0003 | G11: =IF('Input Data '!N12="Y",'PIT PD'!J35,0) -> 0 | H11: 0.65 | I11: =(C11*F11+D11*G11+E11*1)*H11 -> 0
B12: ='PIT PD'!B36 -> A+ | C12: ='Input Data '!T13 -> 2964.5 | D12: ='Input Data '!U13 -> 0 | E12: ='Input Data '!V13 -> 0 | F12: ='PIT PD'!D36 -> 0.0007325299 | G12: =IF('Input Data '!N13="Y",'PIT PD'!J36,0) -> 0 | H12: 0.65 | I12: =(C12*F12+D12*G12+E12*1)*H12 -> 1.4115302
B13: ='PIT PD'!B37 -> A | C13: ='Input Data '!T14 -> 6320.7575 | D13: ='Input Data '!U14 -> 0 | E13: ='Input Data '!V14 -> 0 | F13: ='PIT PD'!D37 -> 0.0007325299 | G13: =IF('Input Data '!N14="Y",'PIT PD'!J37,0) -> 0 | H13: 0.65 | I13: =(C13*F13+D13*G13+E13*1)*H13 -> 3.0095935
B14: ='PIT PD'!B38 -> A- | C14: ='Input Data '!T15 -> 12522.26 | D14: ='Input Data '!U15 -> 0 | E14: ='Input Data '!V15 -> 0 | F14: ='PIT PD'!D38 -> 0.0007325299 | G14: =IF('Input Data '!N15="Y",'PIT PD'!J38,0) -> 0 | H14: 0.65 | I14: =(C14*F14+D14*G14+E14*1)*H14 -> 5.9624044
B15: ='PIT PD'!B39 -> BBB+ | C15: ='Input Data '!T16 -> 2639.75 | D15: ='Input Data '!U16 -> 0 | E15: ='Input Data '!V16 -> 0 | F15: ='PIT PD'!D39 -> 0.0055855585 | G15: =IF('Input Data '!N16="Y",'PIT PD'!J39,0) -> 0 | H15: 0.65 | I15: =(C15*F15+D15*G15+E15*1)*H15 -> 9.5839107
B16: ='PIT PD'!B40 -> BBB | C16: ='Input Data '!T17 -> 0 | D16: ='Input Data '!U17 -> 0 | E16: ='Input Data '!V17 -> 0 | F16: ='PIT PD'!D40 -> 0.0055855585 | G16: =IF('Input Data '!N17="Y",'PIT PD'!J40,0) -> 0 | H16: 0.65 | I16: =(C16*F16+D16*G16+E16*1)*H16 -> 0
B17: ='PIT PD'!B41 -> BBB- | C17: ='Input Data '!T18 -> 0 | D17: ='Input Data '!U18 -> 0 | E17: ='Input Data '!V18 -> 0 | F17: ='PIT PD'!D41 -> 0.0055855585 | G17: =IF('Input Data '!N18="Y",'PIT PD'!J41,0) -> 0 | H17: 0.65 | I17: =(C17*F17+D17*G17+E17*1)*H17 -> 0
B18: ='PIT PD'!B42 -> BB+ | C18: ='Input Data '!T19 -> 2490.41 | D18: ='Input Data '!U19 -> 0 | E18: ='Input Data '!V19 -> 0 | F18: ='PIT PD'!D42 -> 0.048175951 | G18: =IF('Input Data '!N19="Y",'PIT PD'!J42,0) -> 0 | H18: 0.65 | I18: =(C18*F18+D18*G18+E18*1)*H18 -> 77.985615
B19: ='PIT PD'!B43 -> Unrated | C19: ='Input Data '!T20 -> 200 | D19: ='Input Data '!U20 -> 0 | E19: ='Input Data '!V20 -> 0 | F19: ='PIT PD'!D43 -> 0.048175951 | G19: =IF('Input Data '!N20="Y",'PIT PD'!J43,0) -> 0 | H19: 0.65 | I19: =(C19*F19+D19*G19+E19*1)*H19 -> 6.2628736
B20: Total | H20: ECL | I20: =SUM(I8:I19) -> 110.07907

Sheet Assumption
A2: Sr No. | B2: Area | C2: Assumptions
A3: 1 | B3: PD Assumption | C3: In the absence of historical delinquency migration data (DPD bucket movements) to support an internal PD estimate, we have adopted CRISIL's credit rating-based default rates as a proxy for the Through-the-Cycle (TTC) Probability of Default (PD)
A4: 2 | B4: PD Assumption | C4: A minimum PD of 0.03% has been assumed, based on the default rate prescribed by CRISIL for AAA-rated exposures.
A5: 3 | B5: SICR | C5: Since there has been no movement in rating from the date of disbursement to the current date, no significant increase in credit risk has been identified. Therefore, all accounts have been classified as Stage 1.
A6: 4 | B6: LGD | C6: In the absence of historical internal default data, we have adopted the RBI-prescribed LGD rate of 65%. This conservative approach serves as a robust proxy for recovery estimation given the lack of realized loss experience.
A7: 5 | B7: CCF | C7: Taken as input parameter as provided by the client (For undrawn credit facilities, a Credit Conversion Factor (CCF) is applied based on the residual maturity of the commitment: 20% for facilities with a maturity of up to one year, and 50% for those exceeding one year)
A8: 6 | B8: Unrated | C8: For currently unrated exposures, a conservative rating of BB+ has been assigned as a proxy rating to facilitate PD estimation, reflecting the inherent uncertainty associated with the absence of an external rating assessment as of the reporting date.
A9: 7 | B9: MEV Selection | C9: MEV selected based on relevance to the portfolio as per the Policy
A10: 8 | B10: MEV Weights | C10: Weights are assigned to the MEV as per the policy
A11: 9 | B11: ECL | C11: ECL value is floored to the minimum regulatory requirements

Sheet Admin
B4: PD Calibration and Scaling
B5: Confidence Interval | E5: 0.65
B8: Scenario Weights
B9: Base | C9: Upturn | D9: Downturn
B10: 0.5 | C10: 0.05 | D10: 0.45
B13: Scenario Multiplier
B14: 0.9
B15: 1.1
